{
  "skill": "binance-alpha-assistant",
  "generated_at": "2026-05-02T19:19:16.166824+00:00",
  "assumptions": {
    "participant_volume_standard": 8200,
    "alpha_kline_interval": "5m",
    "alpha_kline_limit": 48,
    "recent_listing_hours": 72
  },
  "quadruple_points": {
    "token_count": 12,
    "total_volume_24h": 1246867735.676515,
    "total_alpha_trade_quote_volume_24h": 1246867735.676515,
    "total_alpha_trade_base_volume_24h": 4281308164.0720005,
    "total_token_list_volume24h": 48908987.683890164,
    "estimated_participants": 152057.04093616037,
    "volume_method": "alpha_trade_quote_volume_sum",
    "tokens": [
      {
        "symbol": "GENIUS",
        "name": "Genius",
        "chain_id": "56",
        "contract_address": "0x1f12b85aac097e43aa1555b2881e98a51090e9a6",
        "alpha_id": "ALPHA_887",
        "alpha_trade_symbol": "ALPHA_887USDT",
        "alpha_trade_symbols": [
          "ALPHA_887USDT",
          "ALPHA_887USDC",
          "ALPHA_887U"
        ],
        "alpha_trade_tickers": [
          {
            "symbol": "ALPHA_887USDT",
            "quote_volume24h": 663380129.4431405,
            "base_volume24h": 1314092317.53,
            "last_price": 0.53163191
          },
          {
            "symbol": "ALPHA_887USDC",
            "quote_volume24h": 1104495.26549041,
            "base_volume24h": 2174811.6,
            "last_price": 0.53261744
          },
          {
            "symbol": "ALPHA_887U",
            "quote_volume24h": 263.32600479,
            "base_volume24h": 508.78,
            "last_price": 0.50375625
          }
        ],
        "mul_point": 4,
        "price": 0.5326407666224081,
        "percent_change_24h": 8.45,
        "volume24h": 9322780.907872878,
        "token_list_volume24h": 9322780.907872878,
        "display_volume24h": 664484888.0346357,
        "display_volume_method": "alpha_trade_quote_volume",
        "alpha_trade_quote_volume24h": 664484888.0346357,
        "alpha_trade_base_volume24h": 1316267637.9099998,
        "liquidity": 2009970.501375986,
        "holders": 17688,
        "count24h": 44945,
        "listing_time": "2026-04-13T15:30:00+00:00",
        "listing_time_ms": 1776094200000,
        "amplitude_24h_pct": 20.26604331920353,
        "estimated_participants": 81034.74244324825
      },
      {
        "symbol": "OPG",
        "name": "OpenGradient",
        "chain_id": "56",
        "contract_address": "0x5feccd17c393caf1001d18164236a37e731fcb9d",
        "alpha_id": "ALPHA_931",
        "alpha_trade_symbol": "ALPHA_931USDT",
        "alpha_trade_symbols": [
          "ALPHA_931USDT",
          "ALPHA_931USDC",
          "ALPHA_931U"
        ],
        "alpha_trade_tickers": [
          {
            "symbol": "ALPHA_931USDT",
            "quote_volume24h": 493463533.3292999,
            "base_volume24h": 1982356242.81,
            "last_price": 0.25469331
          },
          {
            "symbol": "ALPHA_931USDC",
            "quote_volume24h": 1026911.32915093,
            "base_volume24h": 4125941.73,
            "last_price": 0.25498653
          },
          {
            "symbol": "ALPHA_931U",
            "quote_volume24h": 18508.28297309,
            "base_volume24h": 75877.09,
            "last_price": 0.2472165
          }
        ],
        "mul_point": 4,
        "price": 0.2546980380255055,
        "percent_change_24h": 5.67,
        "volume24h": 14424482.000627678,
        "token_list_volume24h": 14424482.000627678,
        "display_volume24h": 494508952.94142395,
        "display_volume_method": "alpha_trade_quote_volume",
        "alpha_trade_quote_volume24h": 494508952.94142395,
        "alpha_trade_base_volume24h": 1986558061.6299999,
        "liquidity": 1504983.813381027,
        "holders": 5187,
        "count24h": 56613,
        "listing_time": "2026-04-21T11:00:00+00:00",
        "listing_time_ms": 1776769200000,
        "amplitude_24h_pct": 8.947559848463815,
        "estimated_participants": 60305.96987090536
      },
      {
        "symbol": "ST",
        "name": "Sentio",
        "chain_id": "56",
        "contract_address": "0x70be40667385500c5da7f108a022e21b606045dd",
        "alpha_id": "ALPHA_889",
        "alpha_trade_symbol": "ALPHA_889USDT",
        "alpha_trade_symbols": [
          "ALPHA_889USDT",
          "ALPHA_889USDC",
          "ALPHA_889U"
        ],
        "alpha_trade_tickers": [
          {
            "symbol": "ALPHA_889USDT",
            "quote_volume24h": 86480050.47988547,
            "base_volume24h": 945444124.47,
            "last_price": 0.0823988
          },
          {
            "symbol": "ALPHA_889USDC",
            "quote_volume24h": 327038.26516588,
            "base_volume24h": 3597877.31,
            "last_price": 0.081844
          },
          {
            "symbol": "ALPHA_889U",
            "quote_volume24h": 25.97062715,
            "base_volume24h": 264.13,
            "last_price": 0.09832517
          }
        ],
        "mul_point": 4,
        "price": 0.08210787947737906,
        "percent_change_24h": -9.51,
        "volume24h": 14487653.927734695,
        "token_list_volume24h": 14487653.927734695,
        "display_volume24h": 86807114.7156785,
        "display_volume_method": "alpha_trade_quote_volume",
        "alpha_trade_quote_volume24h": 86807114.7156785,
        "alpha_trade_base_volume24h": 949042265.91,
        "liquidity": 1759321.5465134582,
        "holders": 23829,
        "count24h": 48791,
        "listing_time": "2026-04-15T10:00:00+00:00",
        "listing_time_ms": 1776247200000,
        "amplitude_24h_pct": 26.720381796942718,
        "estimated_participants": 10586.233501912013
      },
      {
        "symbol": "TAC",
        "name": "TAC",
        "chain_id": "56",
        "contract_address": "0x1219c409fabe2c27bd0d1a565daeed9bd9f271de",
        "alpha_id": "ALPHA_277",
        "alpha_trade_symbol": "ALPHA_277USDT",
        "alpha_trade_symbols": [
          "ALPHA_277USDT",
          "ALPHA_277USDC",
          "ALPHA_277U"
        ],
        "alpha_trade_tickers": [
          {
            "symbol": "ALPHA_277USDT",
            "quote_volume24h": 306972.58965782,
            "base_volume24h": 14631219.11,
            "last_price": 0.02077017
          },
          {
            "symbol": "ALPHA_277USDC",
            "quote_volume24h": 18520.05326748,
            "base_volume24h": 854283.48,
            "last_price": 0.02089623
          }
        ],
        "mul_point": 4,
        "price": 0.020836755301363447,
        "percent_change_24h": 23.42,
        "volume24h": 3753855.8250453565,
        "token_list_volume24h": 3753855.8250453565,
        "display_volume24h": 325492.6429253,
        "display_volume_method": "alpha_trade_quote_volume",
        "alpha_trade_quote_volume24h": 325492.6429253,
        "alpha_trade_base_volume24h": 15485502.59,
        "liquidity": 667263.8120726313,
        "holders": 2274,
        "count24h": 28324,
        "listing_time": "2025-07-15T10:00:00+00:00",
        "listing_time_ms": 1752573600000,
        "amplitude_24h_pct": 45.49788407935184,
        "estimated_participants": 39.69422474698781
      },
      {
        "symbol": "SOON",
        "name": "SOON",
        "chain_id": "56",
        "contract_address": "0xb9e1fd5a02d3a33b25a14d661414e6ed6954a721",
        "alpha_id": "ALPHA_199",
        "alpha_trade_symbol": "ALPHA_199USDT",
        "alpha_trade_symbols": [
          "ALPHA_199USDT",
          "ALPHA_199USDC",
          "ALPHA_199U"
        ],
        "alpha_trade_tickers": [
          {
            "symbol": "ALPHA_199USDT",
            "quote_volume24h": 292854.45841223,
            "base_volume24h": 1696911.24,
            "last_price": 0.1750325
          },
          {
            "symbol": "ALPHA_199USDC",
            "quote_volume24h": 11501.23600883,
            "base_volume24h": 66435.82,
            "last_price": 0.17495504
          }
        ],
        "mul_point": 4,
        "price": 0.17504176629924986,
        "percent_change_24h": 2.06,
        "volume24h": 691381.4126737362,
        "token_list_volume24h": 691381.4126737362,
        "display_volume24h": 304355.69442106003,
        "display_volume_method": "alpha_trade_quote_volume",
        "alpha_trade_quote_volume24h": 304355.69442106003,
        "alpha_trade_base_volume24h": 1763347.06,
        "liquidity": 828014.9788295587,
        "holders": 11225,
        "count24h": 3987,
        "listing_time": "2025-11-26T09:00:00+00:00",
        "listing_time_ms": 1764147600000,
        "amplitude_24h_pct": 5.81124639181413,
        "estimated_participants": 37.11654810012927
      },
      {
        "symbol": "UAI",
        "name": "UnifAI Network",
        "chain_id": "56",
        "contract_address": "0x3e5d4f8aee0d9b3082d5f6da5d6e225d17ba9ea0",
        "alpha_id": "ALPHA_461",
        "alpha_trade_symbol": "ALPHA_461USDT",
        "alpha_trade_symbols": [
          "ALPHA_461USDT",
          "ALPHA_461USDC",
          "ALPHA_461U"
        ],
        "alpha_trade_tickers": [
          {
            "symbol": "ALPHA_461USDT",
            "quote_volume24h": 124553.63466011,
            "base_volume24h": 377218.1,
            "last_price": 0.33239025
          },
          {
            "symbol": "ALPHA_461USDC",
            "quote_volume24h": 2188.63735179,
            "base_volume24h": 6670.68,
            "last_price": 0.33781603
          }
        ],
        "mul_point": 4,
        "price": 0.3325688422957716,
        "percent_change_24h": 3.42,
        "volume24h": 1357096.066805337,
        "token_list_volume24h": 1357096.066805337,
        "display_volume24h": 126742.2720119,
        "display_volume_method": "alpha_trade_quote_volume",
        "alpha_trade_quote_volume24h": 126742.2720119,
        "alpha_trade_base_volume24h": 383888.77999999997,
        "liquidity": 937151.3099957472,
        "holders": 5658,
        "count24h": 9579,
        "listing_time": "2025-11-06T11:00:00+00:00",
        "listing_time_ms": 1762426800000,
        "amplitude_24h_pct": 14.001322773758787,
        "estimated_participants": 15.45637463559756
      },
      {
        "symbol": "HANA",
        "name": "Hana Network",
        "chain_id": "56",
        "contract_address": "0x6261963ebe9ff014aad10ecc3b0238d4d04e8353",
        "alpha_id": "ALPHA_394",
        "alpha_trade_symbol": "ALPHA_394USDT",
        "alpha_trade_symbols": [
          "ALPHA_394USDT",
          "ALPHA_394USDC",
          "ALPHA_394U"
        ],
        "alpha_trade_tickers": [
          {
            "symbol": "ALPHA_394USDT",
            "quote_volume24h": 95249.02688441,
            "base_volume24h": 2587519.58,
            "last_price": 0.03674629
          },
          {
            "symbol": "ALPHA_394USDC",
            "quote_volume24h": 2874.85759787,
            "base_volume24h": 77290.04,
            "last_price": 0.03673928
          }
        ],
        "mul_point": 4,
        "price": 0.036694899205334634,
        "percent_change_24h": -3.28,
        "volume24h": 1002438.4422022089,
        "token_list_volume24h": 1002438.4422022089,
        "display_volume24h": 98123.88448228,
        "display_volume_method": "alpha_trade_quote_volume",
        "alpha_trade_quote_volume24h": 98123.88448228,
        "alpha_trade_base_volume24h": 2664809.62,
        "liquidity": 1558571.7272920923,
        "holders": 6550,
        "count24h": 5145,
        "listing_time": "2025-09-26T11:00:00+00:00",
        "listing_time_ms": 1758884400000,
        "amplitude_24h_pct": 9.093831958174087,
        "estimated_participants": 11.966327375887806
      },
      {
        "symbol": "AGT",
        "name": "Alaya Governance Token",
        "chain_id": "56",
        "contract_address": "0x5dbde81fce337ff4bcaaee4ca3466c00aecae274",
        "alpha_id": "ALPHA_191",
        "alpha_trade_symbol": "ALPHA_191USDT",
        "alpha_trade_symbols": [
          "ALPHA_191USDT",
          "ALPHA_191USDC",
          "ALPHA_191U"
        ],
        "alpha_trade_tickers": [
          {
            "symbol": "ALPHA_191USDT",
            "quote_volume24h": 71075.2684699,
            "base_volume24h": 4005313.99,
            "last_price": 0.01743205
          },
          {
            "symbol": "ALPHA_191USDC",
            "quote_volume24h": 19006.82275386,
            "base_volume24h": 1059990.24,
            "last_price": 0.0175517
          }
        ],
        "mul_point": 4,
        "price": 0.017422304168839678,
        "percent_change_24h": 2.76,
        "volume24h": 2296984.6860250514,
        "token_list_volume24h": 2296984.6860250514,
        "display_volume24h": 90082.09122376,
        "display_volume_method": "alpha_trade_quote_volume",
        "alpha_trade_quote_volume24h": 90082.09122376,
        "alpha_trade_base_volume24h": 5065304.23,
        "liquidity": 1249816.0466891974,
        "holders": 189651,
        "count24h": 13213,
        "listing_time": "2025-05-16T09:05:00+00:00",
        "listing_time_ms": 1747386300000,
        "amplitude_24h_pct": 11.973846405855843,
        "estimated_participants": 10.98562088094634
      },
      {
        "symbol": "EVAA",
        "name": "EVAA",
        "chain_id": "56",
        "contract_address": "0xaa036928c9c0df07d525b55ea8ee690bb5a628c1",
        "alpha_id": "ALPHA_409",
        "alpha_trade_symbol": "ALPHA_409USDT",
        "alpha_trade_symbols": [
          "ALPHA_409USDT",
          "ALPHA_409USDC",
          "ALPHA_409U"
        ],
        "alpha_trade_tickers": [
          {
            "symbol": "ALPHA_409USDT",
            "quote_volume24h": 56431.5711898,
            "base_volume24h": 96825.958,
            "last_price": 0.58660756
          },
          {
            "symbol": "ALPHA_409USDC",
            "quote_volume24h": 1349.61609257,
            "base_volume24h": 2308.204,
            "last_price": 0.57966789
          }
        ],
        "mul_point": 4,
        "price": 0.5830408058686528,
        "percent_change_24h": 0.34,
        "volume24h": 1147788.9280330217,
        "token_list_volume24h": 1147788.9280330217,
        "display_volume24h": 57781.18728237,
        "display_volume_method": "alpha_trade_quote_volume",
        "alpha_trade_quote_volume24h": 57781.18728237,
        "alpha_trade_base_volume24h": 99134.162,
        "liquidity": 577525.463881685,
        "holders": 23087,
        "count24h": 8003,
        "listing_time": "2025-10-03T08:00:00+00:00",
        "listing_time_ms": 1759478400000,
        "amplitude_24h_pct": 4.0729181209255385,
        "estimated_participants": 7.0464862539475615
      },
      {
        "symbol": "DAM",
        "name": "Reservoir",
        "chain_id": "56",
        "contract_address": "0xf9ca3fe094212ffa705742d3626a8ab96aababf8",
        "alpha_id": "ALPHA_327",
        "alpha_trade_symbol": "ALPHA_327USDT",
        "alpha_trade_symbols": [
          "ALPHA_327USDT",
          "ALPHA_327USDC",
          "ALPHA_327U"
        ],
        "alpha_trade_tickers": [
          {
            "symbol": "ALPHA_327USDT",
            "quote_volume24h": 34042.48894708,
            "base_volume24h": 2976807.22,
            "last_price": 0.01078994
          },
          {
            "symbol": "ALPHA_327USDC",
            "quote_volume24h": 6896.07030213,
            "base_volume24h": 613053.53,
            "last_price": 0.01101742
          }
        ],
        "mul_point": 4,
        "price": 0.010839644847158408,
        "percent_change_24h": -11.76,
        "volume24h": 217903.5939961907,
        "token_list_volume24h": 217903.5939961907,
        "display_volume24h": 40938.55924921,
        "display_volume_method": "alpha_trade_quote_volume",
        "alpha_trade_quote_volume24h": 40938.55924921,
        "alpha_trade_base_volume24h": 3589860.75,
        "liquidity": 247533.8024088029,
        "holders": 1880,
        "count24h": 2811,
        "listing_time": "2025-08-18T11:00:00+00:00",
        "listing_time_ms": 1755514800000,
        "amplitude_24h_pct": 17.463619197491926,
        "estimated_participants": 4.992507225513414
      },
      {
        "symbol": "CARV",
        "name": "CARV",
        "chain_id": "56",
        "contract_address": "0xc08cd26474722ce93f4d0c34d16201461c10aa8c",
        "alpha_id": "ALPHA_241",
        "alpha_trade_symbol": "ALPHA_241USDT",
        "alpha_trade_symbols": [
          "ALPHA_241USDT",
          "ALPHA_241USDC",
          "ALPHA_241U"
        ],
        "alpha_trade_tickers": [
          {
            "symbol": "ALPHA_241USDT",
            "quote_volume24h": 21716.07753928,
            "base_volume24h": 379666.99,
            "last_price": 0.058
          },
          {
            "symbol": "ALPHA_241USDC",
            "quote_volume24h": 111.78356632,
            "base_volume24h": 1913.37,
            "last_price": 0.0587799
          }
        ],
        "mul_point": 4,
        "price": 0.05832414745474879,
        "percent_change_24h": 5.92,
        "volume24h": 139813.45338793573,
        "token_list_volume24h": 139813.45338793573,
        "display_volume24h": 21827.861105599997,
        "display_volume_method": "alpha_trade_quote_volume",
        "alpha_trade_quote_volume24h": 21827.861105599997,
        "alpha_trade_base_volume24h": 381580.36,
        "liquidity": 221865.49105546274,
        "holders": 116945,
        "count24h": 1119,
        "listing_time": "2025-06-23T07:00:00+00:00",
        "listing_time_ms": 1750662000000,
        "amplitude_24h_pct": 10.38775851447075,
        "estimated_participants": 2.661934281170731
      },
      {
        "symbol": "RION",
        "name": "Hyperion",
        "chain_id": "56",
        "contract_address": "0xc0c240c870606a5cb3150795e2d0dfff9f1f7456",
        "alpha_id": "ALPHA_278",
        "alpha_trade_symbol": "ALPHA_278USDT",
        "alpha_trade_symbols": [
          "ALPHA_278USDT",
          "ALPHA_278USDC",
          "ALPHA_278U"
        ],
        "alpha_trade_tickers": [
          {
            "symbol": "ALPHA_278USDT",
            "quote_volume24h": 831.29154246,
            "base_volume24h": 3981.52,
            "last_price": 0.21
          },
          {
            "symbol": "ALPHA_278USDC",
            "quote_volume24h": 604.50053291,
            "base_volume24h": 2789.55,
            "last_price": 0.217057
          }
        ],
        "mul_point": 4,
        "price": 0.2095733109097006,
        "percent_change_24h": -0.71,
        "volume24h": 66808.4394860605,
        "token_list_volume24h": 66808.4394860605,
        "display_volume24h": 1435.79207537,
        "display_volume_method": "alpha_trade_quote_volume",
        "alpha_trade_quote_volume24h": 1435.79207537,
        "alpha_trade_base_volume24h": 6771.07,
        "liquidity": 813878.0257327068,
        "holders": 16089,
        "count24h": 3173,
        "listing_time": "2025-07-16T13:10:00+00:00",
        "listing_time_ms": 1752671400000,
        "amplitude_24h_pct": 5.207523724659057,
        "estimated_participants": 0.17509659455731708
      }
    ]
  },
  "stable_candidates": {
    "analyzed_count": 3,
    "recommendations": [
      {
        "symbol": "GENIUS",
        "name": "Genius",
        "chain_id": "56",
        "contract_address": "0x1f12b85aac097e43aa1555b2881e98a51090e9a6",
        "alpha_id": "ALPHA_887",
        "alpha_trade_symbol": "ALPHA_887USDT",
        "alpha_trade_symbols": [
          "ALPHA_887USDT",
          "ALPHA_887USDC",
          "ALPHA_887U"
        ],
        "alpha_trade_tickers": [
          {
            "symbol": "ALPHA_887USDT",
            "quote_volume24h": 663380129.4431405,
            "base_volume24h": 1314092317.53,
            "last_price": 0.53163191
          },
          {
            "symbol": "ALPHA_887USDC",
            "quote_volume24h": 1104495.26549041,
            "base_volume24h": 2174811.6,
            "last_price": 0.53261744
          },
          {
            "symbol": "ALPHA_887U",
            "quote_volume24h": 263.32600479,
            "base_volume24h": 508.78,
            "last_price": 0.50375625
          }
        ],
        "mul_point": 4,
        "price": 0.5326407666224081,
        "percent_change_24h": 8.45,
        "volume24h": 9322780.907872878,
        "token_list_volume24h": 9322780.907872878,
        "display_volume24h": 664484888.0346357,
        "display_volume_method": "alpha_trade_quote_volume",
        "alpha_trade_quote_volume24h": 664484888.0346357,
        "alpha_trade_base_volume24h": 1316267637.9099998,
        "liquidity": 2009970.501375986,
        "holders": 17688,
        "count24h": 44945,
        "listing_time": "2026-04-13T15:30:00+00:00",
        "listing_time_ms": 1776094200000,
        "amplitude_24h_pct": 20.26604331920353,
        "estimated_participants": 81034.74244324825,
        "realized_volatility_pct": 0.3693377638022478,
        "amplitude_4h_pct": 4.403280464216624,
        "trend_4h_pct": 2.8301547388781545,
        "stable_volume24h": 664484888.0346357,
        "audit_risk": "LOW",
        "audit_factor": 1.0,
        "stability_score": 94.6,
        "reason": [
          "Alpha Trade 24h 成交额 664,484,888，流动性 2,009,971",
          "Alpha 列表口径 24h 成交额 9,322,781",
          "短周期波动 0.37%",
          "4h 振幅 4.40%",
          "审计风险 LOW"
        ]
      },
      {
        "symbol": "OPG",
        "name": "OpenGradient",
        "chain_id": "56",
        "contract_address": "0x5feccd17c393caf1001d18164236a37e731fcb9d",
        "alpha_id": "ALPHA_931",
        "alpha_trade_symbol": "ALPHA_931USDT",
        "alpha_trade_symbols": [
          "ALPHA_931USDT",
          "ALPHA_931USDC",
          "ALPHA_931U"
        ],
        "alpha_trade_tickers": [
          {
            "symbol": "ALPHA_931USDT",
            "quote_volume24h": 493463533.3292999,
            "base_volume24h": 1982356242.81,
            "last_price": 0.25469331
          },
          {
            "symbol": "ALPHA_931USDC",
            "quote_volume24h": 1026911.32915093,
            "base_volume24h": 4125941.73,
            "last_price": 0.25498653
          },
          {
            "symbol": "ALPHA_931U",
            "quote_volume24h": 18508.28297309,
            "base_volume24h": 75877.09,
            "last_price": 0.2472165
          }
        ],
        "mul_point": 4,
        "price": 0.2546980380255055,
        "percent_change_24h": 5.67,
        "volume24h": 14424482.000627678,
        "token_list_volume24h": 14424482.000627678,
        "display_volume24h": 494508952.94142395,
        "display_volume_method": "alpha_trade_quote_volume",
        "alpha_trade_quote_volume24h": 494508952.94142395,
        "alpha_trade_base_volume24h": 1986558061.6299999,
        "liquidity": 1504983.813381027,
        "holders": 5187,
        "count24h": 56613,
        "listing_time": "2026-04-21T11:00:00+00:00",
        "listing_time_ms": 1776769200000,
        "amplitude_24h_pct": 8.947559848463815,
        "estimated_participants": 60305.96987090536,
        "realized_volatility_pct": 0.4843600597727706,
        "amplitude_4h_pct": 4.195106936322354,
        "trend_4h_pct": 2.067374111402298,
        "stable_volume24h": 494508952.94142395,
        "audit_risk": "LOW",
        "audit_factor": 1.0,
        "stability_score": 52.87,
        "reason": [
          "Alpha Trade 24h 成交额 494,508,953，流动性 1,504,984",
          "Alpha 列表口径 24h 成交额 14,424,482",
          "短周期波动 0.48%",
          "4h 振幅 4.20%",
          "审计风险 LOW"
        ]
      },
      {
        "symbol": "ST",
        "name": "Sentio",
        "chain_id": "56",
        "contract_address": "0x70be40667385500c5da7f108a022e21b606045dd",
        "alpha_id": "ALPHA_889",
        "alpha_trade_symbol": "ALPHA_889USDT",
        "alpha_trade_symbols": [
          "ALPHA_889USDT",
          "ALPHA_889USDC",
          "ALPHA_889U"
        ],
        "alpha_trade_tickers": [
          {
            "symbol": "ALPHA_889USDT",
            "quote_volume24h": 86480050.47988547,
            "base_volume24h": 945444124.47,
            "last_price": 0.0823988
          },
          {
            "symbol": "ALPHA_889USDC",
            "quote_volume24h": 327038.26516588,
            "base_volume24h": 3597877.31,
            "last_price": 0.081844
          },
          {
            "symbol": "ALPHA_889U",
            "quote_volume24h": 25.97062715,
            "base_volume24h": 264.13,
            "last_price": 0.09832517
          }
        ],
        "mul_point": 4,
        "price": 0.08210787947737906,
        "percent_change_24h": -9.51,
        "volume24h": 14487653.927734695,
        "token_list_volume24h": 14487653.927734695,
        "display_volume24h": 86807114.7156785,
        "display_volume_method": "alpha_trade_quote_volume",
        "alpha_trade_quote_volume24h": 86807114.7156785,
        "alpha_trade_base_volume24h": 949042265.91,
        "liquidity": 1759321.5465134582,
        "holders": 23829,
        "count24h": 48791,
        "listing_time": "2026-04-15T10:00:00+00:00",
        "listing_time_ms": 1776247200000,
        "amplitude_24h_pct": 26.720381796942718,
        "estimated_participants": 10586.233501912013,
        "realized_volatility_pct": 0.8509895300736136,
        "amplitude_4h_pct": 8.75559446030949,
        "trend_4h_pct": -3.5588135360921758,
        "stable_volume24h": 86807114.7156785,
        "audit_risk": "LOW",
        "audit_factor": 1.0,
        "stability_score": 35.07,
        "reason": [
          "Alpha Trade 24h 成交额 86,807,115，流动性 1,759,322",
          "Alpha 列表口径 24h 成交额 14,487,654",
          "短周期波动 0.85%",
          "4h 振幅 8.76%",
          "审计风险 LOW"
        ]
      }
    ],
    "summary": [
      "当前最适合稳定刷分的首选是 GENIUS，因为 Alpha Trade 成交额与流动性更高，短周期波动更可控。",
      "稳定刷分分数综合考虑 Alpha Trade 24h 成交额、流动性、持有人、短周期波动、4h 振幅与审计风险。"
    ]
  },
  "futures_alerts": {
    "matched_contract_count": 214,
    "alerts": [
      {
        "alpha_symbol": "G",
        "futures_symbol": "GUSDT",
        "price_change_percent_24h": 23.448,
        "quote_volume_24h": 25498598.812447,
        "funding_bps": -89.9526,
        "base_score": 116.01007589505541,
        "open_interest_change_5m_pct": 0.5560779496203594,
        "alert_score": 116.68,
        "should_notify": true,
        "reasons": [
          "24h 涨跌 23.45%",
          "24h 成交额 25,498,599",
          "资金费率 -89.95 bps",
          "5m 持仓变化 0.56%"
        ]
      },
      {
        "alpha_symbol": "KITE",
        "futures_symbol": "KITEUSDT",
        "price_change_percent_24h": -1.68,
        "quote_volume_24h": 33890314.57601,
        "funding_bps": -75.839,
        "base_score": 86.1652663201227,
        "open_interest_change_5m_pct": 0.0632604658293845,
        "alert_score": 86.24,
        "should_notify": true,
        "reasons": [
          "24h 涨跌 -1.68%",
          "24h 成交额 33,890,315",
          "资金费率 -75.84 bps",
          "5m 持仓变化 0.06%"
        ]
      },
      {
        "alpha_symbol": "LYN",
        "futures_symbol": "LYNUSDT",
        "price_change_percent_24h": -43.709,
        "quote_volume_24h": 207512380.72883,
        "funding_bps": -4.8414,
        "base_score": 57.62195682851299,
        "open_interest_change_5m_pct": 0.08965501286994915,
        "alert_score": 57.73,
        "should_notify": true,
        "reasons": [
          "24h 涨跌 -43.71%",
          "24h 成交额 207,512,381",
          "资金费率 -4.84 bps",
          "5m 持仓变化 0.09%"
        ]
      },
      {
        "alpha_symbol": "ATH",
        "futures_symbol": "ATHUSDT",
        "price_change_percent_24h": 9.888,
        "quote_volume_24h": 30410573.286865,
        "funding_bps": -25.609,
        "base_score": 47.42115413617324,
        "open_interest_change_5m_pct": -0.35947929058970374,
        "alert_score": 47.85,
        "should_notify": true,
        "reasons": [
          "24h 涨跌 9.89%",
          "24h 成交额 30,410,573",
          "资金费率 -25.61 bps",
          "5m 持仓变化 -0.36%"
        ]
      },
      {
        "alpha_symbol": "XAN",
        "futures_symbol": "XANUSDT",
        "price_change_percent_24h": 12.08,
        "quote_volume_24h": 538874196.354261,
        "funding_bps": -15.699200000000001,
        "base_score": 43.00255225399779,
        "open_interest_change_5m_pct": 1.8490547997878082,
        "alert_score": 45.22,
        "should_notify": true,
        "reasons": [
          "24h 涨跌 12.08%",
          "24h 成交额 538,874,196",
          "资金费率 -15.70 bps",
          "5m 持仓变化 1.85%"
        ]
      },
      {
        "alpha_symbol": "DEGEN",
        "futures_symbol": "DEGENUSDT",
        "price_change_percent_24h": 26.429,
        "quote_volume_24h": 20601627.8120007,
        "funding_bps": -0.8525999999999999,
        "base_score": 38.00112338131925,
        "open_interest_change_5m_pct": 0.28869640575743816,
        "alert_score": 38.35,
        "should_notify": true,
        "reasons": [
          "24h 涨跌 26.43%",
          "24h 成交额 20,601,628",
          "资金费率 -0.85 bps",
          "5m 持仓变化 0.29%"
        ]
      },
      {
        "alpha_symbol": "PTB",
        "futures_symbol": "PTBUSDT",
        "price_change_percent_24h": 12.01,
        "quote_volume_24h": 12843759.532313,
        "funding_bps": 12.7273,
        "base_score": 36.70169276493303,
        "open_interest_change_5m_pct": -0.05708890997121463,
        "alert_score": 36.77,
        "should_notify": true,
        "reasons": [
          "24h 涨跌 12.01%",
          "24h 成交额 12,843,760",
          "资金费率 12.73 bps",
          "5m 持仓变化 -0.06%"
        ]
      },
      {
        "alpha_symbol": "ROBO",
        "futures_symbol": "ROBOUSDT",
        "price_change_percent_24h": -7.953,
        "quote_volume_24h": 47367153.93955,
        "funding_bps": -14.1438,
        "base_score": 35.977870039940484,
        "open_interest_change_5m_pct": 0.3526400536827179,
        "alert_score": 36.4,
        "should_notify": true,
        "reasons": [
          "24h 涨跌 -7.95%",
          "24h 成交额 47,367,154",
          "资金费率 -14.14 bps",
          "5m 持仓变化 0.35%"
        ]
      }
    ]
  },
  "daily_brief": {
    "recent_alpha_listings": [],
    "official_updates": [
      {
        "catalog_id": 48,
        "catalog_name": "New Cryptocurrency Listing",
        "articles": [
          {
            "title": "Binance Will Add MegaETH (MEGA) on Earn, Buy Crypto, Convert, VIP Loan, Margin & Futures",
            "code": "cd5899547cf34fb0a09cdc9a1eddee9f",
            "publish_time": "2026-04-30T10:47:58.718000+00:00",
            "support_url": "https://www.binance.com/en/support/announcement/detail/cd5899547cf34fb0a09cdc9a1eddee9f",
            "api_url": "https://www.binance.com/bapi/composite/v1/public/cms/article/detail/query?articleCode=cd5899547cf34fb0a09cdc9a1eddee9f",
            "summary": "This is a general announcement. Products and services referred to here may not be available in your region.&nbsp; Fellow Binancians, Binance is excited to announce that MegaETH (M…"
          },
          {
            "title": "Binance Will List MegaETH (MEGA) with Seed Tag Applied",
            "code": "506a7482e6b94bc58f3e275cb15c2861",
            "publish_time": "2026-04-30T09:07:29.704000+00:00",
            "support_url": "https://www.binance.com/en/support/announcement/detail/506a7482e6b94bc58f3e275cb15c2861",
            "api_url": "https://www.binance.com/bapi/composite/v1/public/cms/article/detail/query?articleCode=506a7482e6b94bc58f3e275cb15c2861",
            "summary": "Note: Please do your own research before making any trades for the aforementioned token outside Binance to avoid any scams and ensure safety of your funds. This is a general annou…"
          },
          {
            "title": "Binance Adds USDT/KZT Spot Trading Pair",
            "code": "51c9c56c7d3141fdac18cb9a152defc8",
            "publish_time": "2026-04-30T05:00:06.261000+00:00",
            "support_url": "https://www.binance.com/en/support/announcement/detail/51c9c56c7d3141fdac18cb9a152defc8",
            "api_url": "https://www.binance.com/bapi/composite/v1/public/cms/article/detail/query?articleCode=51c9c56c7d3141fdac18cb9a152defc8",
            "summary": "This is a general announcement and marketing communication. Products and services referred to here may not be available in your region.&nbsp; Fellow Binancians, To expand the list…"
          }
        ]
      },
      {
        "catalog_id": 49,
        "catalog_name": "Latest Binance News",
        "articles": [
          {
            "title": "Binance Will Extend the Monitoring Tag to Include NFP, NOM, POND, QUICK & VIC on 2026-04-30",
            "code": "629b1970537e45b8801427d3de49a25b",
            "publish_time": "2026-04-30T07:00:05.981000+00:00",
            "support_url": "https://www.binance.com/en/support/announcement/detail/629b1970537e45b8801427d3de49a25b",
            "api_url": "https://www.binance.com/bapi/composite/v1/public/cms/article/detail/query?articleCode=629b1970537e45b8801427d3de49a25b",
            "summary": "This is a general announcement. Products and services referred to here may not be available in your region. Fellow Binancians, Based on recent reviews, Binance will extend the Mon…"
          },
          {
            "title": "Binance Margin will Optimize the Interest Rule for Loans",
            "code": "96692c075f7642e99b28eb7e86c49f94",
            "publish_time": "2026-04-30T02:00:14.377000+00:00",
            "support_url": "https://www.binance.com/en/support/announcement/detail/96692c075f7642e99b28eb7e86c49f94",
            "api_url": "https://www.binance.com/bapi/composite/v1/public/cms/article/detail/query?articleCode=96692c075f7642e99b28eb7e86c49f94",
            "summary": "This is a general announcement. Products and services referred to here may not be available in your region. Fellow Binancians, To improve clarity and align interest charges more c…"
          },
          {
            "title": "Binance Earn Yield Arena: Earn Up to 35% APR With This Week’s New Limited-Time Offers! (2026-04-29)",
            "code": "ee4030a109a049aa94544e4b4e90240b",
            "publish_time": "2026-04-29T08:00:10.676000+00:00",
            "support_url": "https://www.binance.com/en/support/announcement/detail/ee4030a109a049aa94544e4b4e90240b",
            "api_url": "https://www.binance.com/bapi/composite/v1/public/cms/article/detail/query?articleCode=ee4030a109a049aa94544e4b4e90240b",
            "summary": "This is a general announcement and marketing communication. Products and services referred to here may not be available in your region.&nbsp; Fellow Binancians,&nbsp; Binance Earn…"
          }
        ]
      },
      {
        "catalog_id": 93,
        "catalog_name": "Latest Activities",
        "articles": [
          {
            "title": "Binance Ai: Join the Discord AMA & Win Rewards",
            "code": "07f001ac2f8e4d6bad52f048319d0281",
            "publish_time": "2026-04-30T13:00:02.749000+00:00",
            "support_url": "https://www.binance.com/en/support/announcement/detail/07f001ac2f8e4d6bad52f048319d0281",
            "api_url": "https://www.binance.com/bapi/composite/v1/public/cms/article/detail/query?articleCode=07f001ac2f8e4d6bad52f048319d0281",
            "summary": "This is a general announcement. Products and services referred to here may not be available in your region. Fellow Binancians, Join us tomorrow on Binance Discord for an exclusive…"
          },
          {
            "title": "Acurast Trading Competition: Trade Acurast (ACU) and Share $200K Worth of Rewards (2026-04-30)",
            "code": "2ef9da217b8a4507a33861f4b74795f8",
            "publish_time": "2026-04-30T11:00:04.274000+00:00",
            "support_url": "https://www.binance.com/en/support/announcement/detail/2ef9da217b8a4507a33861f4b74795f8",
            "api_url": "https://www.binance.com/bapi/composite/v1/public/cms/article/detail/query?articleCode=2ef9da217b8a4507a33861f4b74795f8",
            "summary": "This is a general announcement. Products and services referred to here may not be available in your region. Terms and conditions apply.&nbsp; Fellow Binancians,&nbsp; Binance Wall…"
          },
          {
            "title": "Learn & Earn: Complete the Quiz to Share Sonic (S) Token Rewards!",
            "code": "1f4d3748796348679d6287d06527bbcc",
            "publish_time": "2026-04-30T09:00:01.663000+00:00",
            "support_url": "https://www.binance.com/en/support/announcement/detail/1f4d3748796348679d6287d06527bbcc",
            "api_url": "https://www.binance.com/bapi/composite/v1/public/cms/article/detail/query?articleCode=1f4d3748796348679d6287d06527bbcc",
            "summary": "This is a general announcement. Products and services referred to here may not be available in your region. Fellow Binancians, Binance is excited to announce the next round of \" B…"
          }
        ]
      }
    ],
    "summary": [
      "官方最新上新关注：Binance Will Add MegaETH (MEGA) on Earn, Buy Crypto, Convert, VIP Loan, Margin & Futures",
      "Latest Binance News：Binance Will Extend the Monitoring Tag to Include NFP, NOM, POND, QUICK & VIC on 2026-04-30",
      "Latest Activities：Binance Ai: Join the Discord AMA & Win Rewards"
    ]
  },
  "warnings": [
    "alpha_ticker:ALPHA_199U: request failed code=-1121 url=https://www.binance.com/bapi/defi/v1/public/alpha-trade/ticker",
    "alpha_ticker:ALPHA_461U: request failed code=-1121 url=https://www.binance.com/bapi/defi/v1/public/alpha-trade/ticker",
    "alpha_ticker:ALPHA_409U: request failed code=-1121 url=https://www.binance.com/bapi/defi/v1/public/alpha-trade/ticker",
    "alpha_ticker:ALPHA_394U: request failed code=-1121 url=https://www.binance.com/bapi/defi/v1/public/alpha-trade/ticker",
    "alpha_ticker:ALPHA_327U: request failed code=-1121 url=https://www.binance.com/bapi/defi/v1/public/alpha-trade/ticker",
    "alpha_ticker:ALPHA_278U: request failed code=-1121 url=https://www.binance.com/bapi/defi/v1/public/alpha-trade/ticker",
    "alpha_ticker:ALPHA_277U: request failed code=-1121 url=https://www.binance.com/bapi/defi/v1/public/alpha-trade/ticker",
    "alpha_ticker:ALPHA_241U: request failed code=-1121 url=https://www.binance.com/bapi/defi/v1/public/alpha-trade/ticker",
    "alpha_ticker:ALPHA_191U: request failed code=-1121 url=https://www.binance.com/bapi/defi/v1/public/alpha-trade/ticker",
    "futures_fallback: using previous valid futures snapshot"
  ]
}