{
  "skill": "binance-alpha-assistant",
  "generated_at": "2026-03-25T06:13:28.317100+00:00",
  "assumptions": {
    "participant_volume_standard": 8200,
    "alpha_kline_interval": "5m",
    "alpha_kline_limit": 48,
    "recent_listing_hours": 72
  },
  "quadruple_points": {
    "token_count": 12,
    "total_volume_24h": 1604440029.2670145,
    "total_alpha_trade_quote_volume_24h": 1604440029.2670145,
    "total_alpha_trade_base_volume_24h": 8740626871.88,
    "total_token_list_volume24h": 79428286.59912652,
    "estimated_participants": 195663.41820329445,
    "volume_method": "alpha_trade_quote_volume_sum",
    "tokens": [
      {
        "symbol": "GUA",
        "name": "SUPERFORTUNE",
        "chain_id": "56",
        "contract_address": "0xa5c8e1513b6a08334b479fe4d71f1253259469be",
        "alpha_id": "ALPHA_483",
        "alpha_trade_symbol": "ALPHA_483USDT",
        "alpha_trade_symbols": [
          "ALPHA_483USDT",
          "ALPHA_483USDC"
        ],
        "alpha_trade_tickers": [
          {
            "symbol": "ALPHA_483USDT",
            "quote_volume24h": 1204201244.4168057,
            "base_volume24h": 3930921443.96,
            "last_price": 0.30685564
          },
          {
            "symbol": "ALPHA_483USDC",
            "quote_volume24h": 1880529.21748517,
            "base_volume24h": 6144961.97,
            "last_price": 0.30671966
          }
        ],
        "mul_point": 4,
        "price": 0.30664196392306897,
        "percent_change_24h": -1.19,
        "volume24h": 5706942.558244922,
        "token_list_volume24h": 5706942.558244922,
        "display_volume24h": 1206081773.634291,
        "display_volume_method": "alpha_trade_quote_volume",
        "alpha_trade_quote_volume24h": 1206081773.634291,
        "alpha_trade_base_volume24h": 3937066405.93,
        "liquidity": 2245940.9309382117,
        "holders": 14416,
        "count24h": 20720,
        "listing_time": "2026-02-24T10:00:00+00:00",
        "listing_time_ms": 1771927200000,
        "amplitude_24h_pct": 5.34997291552783,
        "estimated_participants": 147083.14312613304
      },
      {
        "symbol": "BSB",
        "name": "Block Street",
        "chain_id": "56",
        "contract_address": "0x595deaad1eb5476ff1e649fdb7efc36f1e4679cc",
        "alpha_id": "ALPHA_790",
        "alpha_trade_symbol": "ALPHA_790USDT",
        "alpha_trade_symbols": [
          "ALPHA_790USDT",
          "ALPHA_790USDC"
        ],
        "alpha_trade_tickers": [
          {
            "symbol": "ALPHA_790USDT",
            "quote_volume24h": 199617998.8646925,
            "base_volume24h": 2364571272.84,
            "last_price": 0.08316507
          },
          {
            "symbol": "ALPHA_790USDC",
            "quote_volume24h": 150070.93085071,
            "base_volume24h": 1796605.87,
            "last_price": 0.08305884
          }
        ],
        "mul_point": 4,
        "price": 0.08310947107001651,
        "percent_change_24h": -3.31,
        "volume24h": 40067115.67042453,
        "token_list_volume24h": 40067115.67042453,
        "display_volume24h": 199768069.79554322,
        "display_volume_method": "alpha_trade_quote_volume",
        "alpha_trade_quote_volume24h": 199768069.79554322,
        "alpha_trade_base_volume24h": 2366367878.71,
        "liquidity": 1183745.3690921052,
        "holders": 54274,
        "count24h": 91447,
        "listing_time": "2026-03-04T10:00:00+00:00",
        "listing_time_ms": 1772618400000,
        "amplitude_24h_pct": 8.75967262975353,
        "estimated_participants": 24361.959731163806
      },
      {
        "symbol": "UP",
        "name": "Unitas",
        "chain_id": "56",
        "contract_address": "0x000008d2175f9aeaddb2430c26f8a6f73c5a0000",
        "alpha_id": "ALPHA_804",
        "alpha_trade_symbol": "ALPHA_804USDT",
        "alpha_trade_symbols": [
          "ALPHA_804USDT",
          "ALPHA_804USDC"
        ],
        "alpha_trade_tickers": [
          {
            "symbol": "ALPHA_804USDT",
            "quote_volume24h": 165235966.11155745,
            "base_volume24h": 1220729557.64,
            "last_price": 0.13708
          },
          {
            "symbol": "ALPHA_804USDC",
            "quote_volume24h": 106498.23213807,
            "base_volume24h": 795195.06,
            "last_price": 0.13677654
          }
        ],
        "mul_point": 4,
        "price": 0.13707509471390728,
        "percent_change_24h": 3.63,
        "volume24h": 7218681.891227063,
        "token_list_volume24h": 7218681.891227063,
        "display_volume24h": 165342464.34369552,
        "display_volume_method": "alpha_trade_quote_volume",
        "alpha_trade_quote_volume24h": 165342464.34369552,
        "alpha_trade_base_volume24h": 1221524752.7,
        "liquidity": 1963053.7384584523,
        "holders": 11434,
        "count24h": 20710,
        "listing_time": "2026-03-13T10:00:00+00:00",
        "listing_time_ms": 1773396000000,
        "amplitude_24h_pct": 7.5586183599811365,
        "estimated_participants": 20163.71516386531
      },
      {
        "symbol": "BTW",
        "name": "Bitway",
        "chain_id": "56",
        "contract_address": "0x444045b0ee1ee319a660a5e3d604ca0ffa35acaa",
        "alpha_id": "ALPHA_778",
        "alpha_trade_symbol": "ALPHA_778USDT",
        "alpha_trade_symbols": [
          "ALPHA_778USDT",
          "ALPHA_778USDC"
        ],
        "alpha_trade_tickers": [
          {
            "symbol": "ALPHA_778USDT",
            "quote_volume24h": 30212783.75515114,
            "base_volume24h": 1114966455.5,
            "last_price": 0.02797279
          },
          {
            "symbol": "ALPHA_778USDC",
            "quote_volume24h": 75283.92522349,
            "base_volume24h": 2775672.82,
            "last_price": 0.02793425
          }
        ],
        "mul_point": 4,
        "price": 0.027858122236653918,
        "percent_change_24h": -4.2,
        "volume24h": 1660865.2324456857,
        "token_list_volume24h": 1660865.2324456857,
        "display_volume24h": 30288067.68037463,
        "display_volume_method": "alpha_trade_quote_volume",
        "alpha_trade_quote_volume24h": 30288067.68037463,
        "alpha_trade_base_volume24h": 1117742128.32,
        "liquidity": 1170662.7976370356,
        "holders": 7743,
        "count24h": 22077,
        "listing_time": "2026-03-02T08:00:00+00:00",
        "listing_time_ms": 1772438400000,
        "amplitude_24h_pct": 21.230071426927786,
        "estimated_participants": 3693.666790289589
      },
      {
        "symbol": "LYN",
        "name": "Everlyn AI",
        "chain_id": "56",
        "contract_address": "0x302dfaf2cdbe51a18d97186a7384e87cf599877d",
        "alpha_id": "ALPHA_412",
        "alpha_trade_symbol": "ALPHA_412USDT",
        "alpha_trade_symbols": [
          "ALPHA_412USDT",
          "ALPHA_412USDC"
        ],
        "alpha_trade_tickers": [
          {
            "symbol": "ALPHA_412USDT",
            "quote_volume24h": 1053126.7942596,
            "base_volume24h": 15331217.83,
            "last_price": 0.06584163
          },
          {
            "symbol": "ALPHA_412USDC",
            "quote_volume24h": 161942.11255477,
            "base_volume24h": 2380089.98,
            "last_price": 0.06598366
          }
        ],
        "mul_point": 4,
        "price": 0.06581227856479939,
        "percent_change_24h": -3.35,
        "volume24h": 2376424.039138264,
        "token_list_volume24h": 2376424.039138264,
        "display_volume24h": 1215068.90681437,
        "display_volume_method": "alpha_trade_quote_volume",
        "alpha_trade_quote_volume24h": 1215068.90681437,
        "alpha_trade_base_volume24h": 17711307.81,
        "liquidity": 374790.4208355138,
        "holders": 23334,
        "count24h": 33391,
        "listing_time": "2026-02-25T10:00:00+00:00",
        "listing_time_ms": 1772013600000,
        "amplitude_24h_pct": 18.714428569013638,
        "estimated_participants": 148.1791349773622
      },
      {
        "symbol": "CYS",
        "name": "Cysic",
        "chain_id": "56",
        "contract_address": "0x0c69199c1562233640e0db5ce2c399a88eb507c7",
        "alpha_id": "ALPHA_495",
        "alpha_trade_symbol": "ALPHA_495USDT",
        "alpha_trade_symbols": [
          "ALPHA_495USDT",
          "ALPHA_495USDC"
        ],
        "alpha_trade_tickers": [
          {
            "symbol": "ALPHA_495USDT",
            "quote_volume24h": 623193.35947572,
            "base_volume24h": 1050738.27,
            "last_price": 0.5732183
          },
          {
            "symbol": "ALPHA_495USDC",
            "quote_volume24h": 52071.14888131,
            "base_volume24h": 88167.35,
            "last_price": 0.57077208
          }
        ],
        "mul_point": 4,
        "price": 0.5750004339076593,
        "percent_change_24h": -14.3,
        "volume24h": 11043825.086401975,
        "token_list_volume24h": 11043825.086401975,
        "display_volume24h": 675264.50835703,
        "display_volume_method": "alpha_trade_quote_volume",
        "alpha_trade_quote_volume24h": 675264.50835703,
        "alpha_trade_base_volume24h": 1138905.62,
        "liquidity": 1708527.6378618146,
        "holders": 8844,
        "count24h": 39519,
        "listing_time": "2026-03-20T08:00:00+00:00",
        "listing_time_ms": 1773993600000,
        "amplitude_24h_pct": 27.45210318991797,
        "estimated_participants": 82.34933028744268
      },
      {
        "symbol": "SIGMA",
        "name": "SigmaDotMoney",
        "chain_id": "56",
        "contract_address": "0x85375d3e9c4a39350f1140280a8b0de6890a40e7",
        "alpha_id": "ALPHA_439",
        "alpha_trade_symbol": "ALPHA_439USDT",
        "alpha_trade_symbols": [
          "ALPHA_439USDT",
          "ALPHA_439USDC"
        ],
        "alpha_trade_tickers": [
          {
            "symbol": "ALPHA_439USDT",
            "quote_volume24h": 347478.88422213,
            "base_volume24h": 4860796.92,
            "last_price": 0.07864076
          },
          {
            "symbol": "ALPHA_439USDC",
            "quote_volume24h": 14061.84285543,
            "base_volume24h": 197550.4,
            "last_price": 0.07795499
          }
        ],
        "mul_point": 4,
        "price": 0.07881181887907145,
        "percent_change_24h": -6.8,
        "volume24h": 4859088.315161723,
        "token_list_volume24h": 4859088.315161723,
        "display_volume24h": 361540.72707756,
        "display_volume_method": "alpha_trade_quote_volume",
        "alpha_trade_quote_volume24h": 361540.72707756,
        "alpha_trade_base_volume24h": 5058347.32,
        "liquidity": 784307.4382656649,
        "holders": 11011,
        "count24h": 40101,
        "listing_time": "2026-03-10T00:00:00+00:00",
        "listing_time_ms": 1773100800000,
        "amplitude_24h_pct": 31.9723175882552,
        "estimated_participants": 44.09033257043414
      },
      {
        "symbol": "AIA",
        "name": "DeAgentAI",
        "chain_id": "56",
        "contract_address": "0x53ec33cd4fa46b9eced9ca3f6db626c5ffcd55cc",
        "alpha_id": "ALPHA_496",
        "alpha_trade_symbol": "ALPHA_496USDT",
        "alpha_trade_symbols": [
          "ALPHA_496USDT",
          "ALPHA_496USDC"
        ],
        "alpha_trade_tickers": [
          {
            "symbol": "ALPHA_496USDT",
            "quote_volume24h": 316410.61798185,
            "base_volume24h": 3552631.03,
            "last_price": 0.096
          },
          {
            "symbol": "ALPHA_496USDC",
            "quote_volume24h": 9877.65912089,
            "base_volume24h": 111178.02,
            "last_price": 0.094743
          }
        ],
        "mul_point": 4,
        "price": 0.09606521862486851,
        "percent_change_24h": 7.79,
        "volume24h": 2247605.503605833,
        "token_list_volume24h": 2247605.503605833,
        "display_volume24h": 326288.27710274,
        "display_volume_method": "alpha_trade_quote_volume",
        "alpha_trade_quote_volume24h": 326288.27710274,
        "alpha_trade_base_volume24h": 3663809.05,
        "liquidity": 812147.8609354197,
        "holders": 2402,
        "count24h": 17429,
        "listing_time": "2026-03-10T00:00:00+00:00",
        "listing_time_ms": 1773100800000,
        "amplitude_24h_pct": 12.505691712751412,
        "estimated_participants": 39.791253305212194
      },
      {
        "symbol": "BLUAI",
        "name": "Bluwhale",
        "chain_id": "56",
        "contract_address": "0xed9ae3def8d6f052971bb8b6d1975ff267cf9aad",
        "alpha_id": "ALPHA_438",
        "alpha_trade_symbol": "ALPHA_438USDT",
        "alpha_trade_symbols": [
          "ALPHA_438USDT",
          "ALPHA_438USDC"
        ],
        "alpha_trade_tickers": [
          {
            "symbol": "ALPHA_438USDT",
            "quote_volume24h": 194267.1284739,
            "base_volume24h": 29116719.91,
            "last_price": 0.00631569
          },
          {
            "symbol": "ALPHA_438USDC",
            "quote_volume24h": 8968.70009624,
            "base_volume24h": 1381614.42,
            "last_price": 0.00635458
          }
        ],
        "mul_point": 4,
        "price": 0.006326440438729656,
        "percent_change_24h": -14.72,
        "volume24h": 319706.56843325065,
        "token_list_volume24h": 319706.56843325065,
        "display_volume24h": 203235.82857014,
        "display_volume_method": "alpha_trade_quote_volume",
        "alpha_trade_quote_volume24h": 203235.82857014,
        "alpha_trade_base_volume24h": 30498334.33,
        "liquidity": 620421.0492728931,
        "holders": 40890,
        "count24h": 10342,
        "listing_time": "2026-03-05T00:00:00+00:00",
        "listing_time_ms": 1772668800000,
        "amplitude_24h_pct": 31.9761588604454,
        "estimated_participants": 24.7848571427
      },
      {
        "symbol": "LAB",
        "name": "LAB",
        "chain_id": "56",
        "contract_address": "0x7ec43cf65f1663f820427c62a5780b8f2e25593a",
        "alpha_id": "ALPHA_428",
        "alpha_trade_symbol": "ALPHA_428USDT",
        "alpha_trade_symbols": [
          "ALPHA_428USDT",
          "ALPHA_428USDC"
        ],
        "alpha_trade_tickers": [
          {
            "symbol": "ALPHA_428USDT",
            "quote_volume24h": 85781.62507014,
            "base_volume24h": 429674.65,
            "last_price": 0.199881
          },
          {
            "symbol": "ALPHA_428USDC",
            "quote_volume24h": 1909.94277007,
            "base_volume24h": 9447.31,
            "last_price": 0.20137637
          }
        ],
        "mul_point": 4,
        "price": 0.19999760997080654,
        "percent_change_24h": -5.33,
        "volume24h": 2589360.377840257,
        "token_list_volume24h": 2589360.377840257,
        "display_volume24h": 87691.56784021,
        "display_volume_method": "alpha_trade_quote_volume",
        "alpha_trade_quote_volume24h": 87691.56784021,
        "alpha_trade_base_volume24h": 439121.96,
        "liquidity": 1819904.3645557684,
        "holders": 16914,
        "count24h": 19938,
        "listing_time": "2026-03-10T10:00:00+00:00",
        "listing_time_ms": 1773136800000,
        "amplitude_24h_pct": 11.597567008972351,
        "estimated_participants": 10.694093639050001
      },
      {
        "symbol": "SN3",
        "name": "Nebula3",
        "chain_id": "56",
        "contract_address": "0xf758cfb1467a227516d73d87da7d36e7cb6f71f1",
        "alpha_id": "ALPHA_798",
        "alpha_trade_symbol": "ALPHA_798USDT",
        "alpha_trade_symbols": [
          "ALPHA_798USDT",
          "ALPHA_798USDC"
        ],
        "alpha_trade_tickers": [
          {
            "symbol": "ALPHA_798USDT",
            "quote_volume24h": 47026.48585608,
            "base_volume24h": 27396591.02,
            "last_price": 0.00161374
          },
          {
            "symbol": "ALPHA_798USDC",
            "quote_volume24h": 20091.7797128,
            "base_volume24h": 11619918.91,
            "last_price": 0.00158242
          }
        ],
        "mul_point": 4,
        "price": 0.001611689180830669,
        "percent_change_24h": 2.86,
        "volume24h": 164045.93170852808,
        "token_list_volume24h": 164045.93170852808,
        "display_volume24h": 67118.26556888,
        "display_volume_method": "alpha_trade_quote_volume",
        "alpha_trade_quote_volume24h": 67118.26556888,
        "alpha_trade_base_volume24h": 39016509.93,
        "liquidity": 147761.88009763215,
        "holders": 1795,
        "count24h": 1854,
        "listing_time": "2026-03-11T08:00:00+00:00",
        "listing_time_ms": 1773216000000,
        "amplitude_24h_pct": 31.06839149312666,
        "estimated_participants": 8.185154337668292
      },
      {
        "symbol": "IN",
        "name": "INFINIT",
        "chain_id": "56",
        "contract_address": "0x61fac5f038515572d6f42d4bcb6b581642753d50",
        "alpha_id": "ALPHA_312",
        "alpha_trade_symbol": "ALPHA_312USDT",
        "alpha_trade_symbols": [
          "ALPHA_312USDT",
          "ALPHA_312USDC"
        ],
        "alpha_trade_tickers": [
          {
            "symbol": "ALPHA_312USDT",
            "quote_volume24h": 21654.70990959,
            "base_volume24h": 368887.24,
            "last_price": 0.058679
          },
          {
            "symbol": "ALPHA_312USDC",
            "quote_volume24h": 1791.02186967,
            "base_volume24h": 30482.96,
            "last_price": 0.05958
          }
        ],
        "mul_point": 4,
        "price": 0.05874872778759127,
        "percent_change_24h": 0.19,
        "volume24h": 1174625.4244944884,
        "token_list_volume24h": 1174625.4244944884,
        "display_volume24h": 23445.73177926,
        "display_volume_method": "alpha_trade_quote_volume",
        "alpha_trade_quote_volume24h": 23445.73177926,
        "alpha_trade_base_volume24h": 399370.2,
        "liquidity": 1733993.0107537583,
        "holders": 16434,
        "count24h": 10874,
        "listing_time": "2026-03-05T00:00:00+00:00",
        "listing_time_ms": 1772668800000,
        "amplitude_24h_pct": 3.5309740906018017,
        "estimated_participants": 2.8592355828365856
      }
    ]
  },
  "stable_candidates": {
    "analyzed_count": 6,
    "recommendations": [
      {
        "symbol": "GUA",
        "name": "SUPERFORTUNE",
        "chain_id": "56",
        "contract_address": "0xa5c8e1513b6a08334b479fe4d71f1253259469be",
        "alpha_id": "ALPHA_483",
        "alpha_trade_symbol": "ALPHA_483USDT",
        "alpha_trade_symbols": [
          "ALPHA_483USDT",
          "ALPHA_483USDC"
        ],
        "alpha_trade_tickers": [
          {
            "symbol": "ALPHA_483USDT",
            "quote_volume24h": 1204201244.4168057,
            "base_volume24h": 3930921443.96,
            "last_price": 0.30685564
          },
          {
            "symbol": "ALPHA_483USDC",
            "quote_volume24h": 1880529.21748517,
            "base_volume24h": 6144961.97,
            "last_price": 0.30671966
          }
        ],
        "mul_point": 4,
        "price": 0.30664196392306897,
        "percent_change_24h": -1.19,
        "volume24h": 5706942.558244922,
        "token_list_volume24h": 5706942.558244922,
        "display_volume24h": 1206081773.634291,
        "display_volume_method": "alpha_trade_quote_volume",
        "alpha_trade_quote_volume24h": 1206081773.634291,
        "alpha_trade_base_volume24h": 3937066405.93,
        "liquidity": 2245940.9309382117,
        "holders": 14416,
        "count24h": 20720,
        "listing_time": "2026-02-24T10:00:00+00:00",
        "listing_time_ms": 1771927200000,
        "amplitude_24h_pct": 5.34997291552783,
        "estimated_participants": 147083.14312613304,
        "realized_volatility_pct": 0.0973448028014233,
        "amplitude_4h_pct": 0.8634000700831328,
        "trend_4h_pct": 0.1761218238784945,
        "stable_volume24h": 1206081773.634291,
        "audit_risk": "LOW",
        "audit_factor": 1.0,
        "stability_score": 87.15,
        "reason": [
          "Alpha Trade 24h 成交额 1,206,081,774，流动性 2,245,941",
          "Alpha 列表口径 24h 成交额 5,706,943",
          "短周期波动 0.10%",
          "4h 振幅 0.86%",
          "审计风险 LOW"
        ]
      },
      {
        "symbol": "BSB",
        "name": "Block Street",
        "chain_id": "56",
        "contract_address": "0x595deaad1eb5476ff1e649fdb7efc36f1e4679cc",
        "alpha_id": "ALPHA_790",
        "alpha_trade_symbol": "ALPHA_790USDT",
        "alpha_trade_symbols": [
          "ALPHA_790USDT",
          "ALPHA_790USDC"
        ],
        "alpha_trade_tickers": [
          {
            "symbol": "ALPHA_790USDT",
            "quote_volume24h": 199617998.8646925,
            "base_volume24h": 2364571272.84,
            "last_price": 0.08316507
          },
          {
            "symbol": "ALPHA_790USDC",
            "quote_volume24h": 150070.93085071,
            "base_volume24h": 1796605.87,
            "last_price": 0.08305884
          }
        ],
        "mul_point": 4,
        "price": 0.08310947107001651,
        "percent_change_24h": -3.31,
        "volume24h": 40067115.67042453,
        "token_list_volume24h": 40067115.67042453,
        "display_volume24h": 199768069.79554322,
        "display_volume_method": "alpha_trade_quote_volume",
        "alpha_trade_quote_volume24h": 199768069.79554322,
        "alpha_trade_base_volume24h": 2366367878.71,
        "liquidity": 1183745.3690921052,
        "holders": 54274,
        "count24h": 91447,
        "listing_time": "2026-03-04T10:00:00+00:00",
        "listing_time_ms": 1772618400000,
        "amplitude_24h_pct": 8.75967262975353,
        "estimated_participants": 24361.959731163806,
        "realized_volatility_pct": 0.1958937319669351,
        "amplitude_4h_pct": 1.4411836942754763,
        "trend_4h_pct": 0.698442532403365,
        "stable_volume24h": 199768069.79554322,
        "audit_risk": "LOW",
        "audit_factor": 1.0,
        "stability_score": 64.22,
        "reason": [
          "Alpha Trade 24h 成交额 199,768,070，流动性 1,183,745",
          "Alpha 列表口径 24h 成交额 40,067,116",
          "短周期波动 0.20%",
          "4h 振幅 1.44%",
          "审计风险 LOW"
        ]
      },
      {
        "symbol": "UP",
        "name": "Unitas",
        "chain_id": "56",
        "contract_address": "0x000008d2175f9aeaddb2430c26f8a6f73c5a0000",
        "alpha_id": "ALPHA_804",
        "alpha_trade_symbol": "ALPHA_804USDT",
        "alpha_trade_symbols": [
          "ALPHA_804USDT",
          "ALPHA_804USDC"
        ],
        "alpha_trade_tickers": [
          {
            "symbol": "ALPHA_804USDT",
            "quote_volume24h": 165235966.11155745,
            "base_volume24h": 1220729557.64,
            "last_price": 0.13708
          },
          {
            "symbol": "ALPHA_804USDC",
            "quote_volume24h": 106498.23213807,
            "base_volume24h": 795195.06,
            "last_price": 0.13677654
          }
        ],
        "mul_point": 4,
        "price": 0.13707509471390728,
        "percent_change_24h": 3.63,
        "volume24h": 7218681.891227063,
        "token_list_volume24h": 7218681.891227063,
        "display_volume24h": 165342464.34369552,
        "display_volume_method": "alpha_trade_quote_volume",
        "alpha_trade_quote_volume24h": 165342464.34369552,
        "alpha_trade_base_volume24h": 1221524752.7,
        "liquidity": 1963053.7384584523,
        "holders": 11434,
        "count24h": 20710,
        "listing_time": "2026-03-13T10:00:00+00:00",
        "listing_time_ms": 1773396000000,
        "amplitude_24h_pct": 7.5586183599811365,
        "estimated_participants": 20163.71516386531,
        "realized_volatility_pct": 0.20493223759601756,
        "amplitude_4h_pct": 1.5841871956979776,
        "trend_4h_pct": -0.3507521255722845,
        "stable_volume24h": 165342464.34369552,
        "audit_risk": "MID",
        "audit_factor": 0.6,
        "stability_score": 53.59,
        "reason": [
          "Alpha Trade 24h 成交额 165,342,464，流动性 1,963,054",
          "Alpha 列表口径 24h 成交额 7,218,682",
          "短周期波动 0.20%",
          "4h 振幅 1.58%",
          "审计风险 MID"
        ]
      },
      {
        "symbol": "CYS",
        "name": "Cysic",
        "chain_id": "56",
        "contract_address": "0x0c69199c1562233640e0db5ce2c399a88eb507c7",
        "alpha_id": "ALPHA_495",
        "alpha_trade_symbol": "ALPHA_495USDT",
        "alpha_trade_symbols": [
          "ALPHA_495USDT",
          "ALPHA_495USDC"
        ],
        "alpha_trade_tickers": [
          {
            "symbol": "ALPHA_495USDT",
            "quote_volume24h": 623193.35947572,
            "base_volume24h": 1050738.27,
            "last_price": 0.5732183
          },
          {
            "symbol": "ALPHA_495USDC",
            "quote_volume24h": 52071.14888131,
            "base_volume24h": 88167.35,
            "last_price": 0.57077208
          }
        ],
        "mul_point": 4,
        "price": 0.5750004339076593,
        "percent_change_24h": -14.3,
        "volume24h": 11043825.086401975,
        "token_list_volume24h": 11043825.086401975,
        "display_volume24h": 675264.50835703,
        "display_volume_method": "alpha_trade_quote_volume",
        "alpha_trade_quote_volume24h": 675264.50835703,
        "alpha_trade_base_volume24h": 1138905.62,
        "liquidity": 1708527.6378618146,
        "holders": 8844,
        "count24h": 39519,
        "listing_time": "2026-03-20T08:00:00+00:00",
        "listing_time_ms": 1773993600000,
        "amplitude_24h_pct": 27.45210318991797,
        "estimated_participants": 82.34933028744268,
        "realized_volatility_pct": 0.6185571218071094,
        "amplitude_4h_pct": 4.507920816165467,
        "trend_4h_pct": -3.0267215785419577,
        "stable_volume24h": 675264.50835703,
        "audit_risk": "MID",
        "audit_factor": 0.6,
        "stability_score": 31.09,
        "reason": [
          "Alpha Trade 24h 成交额 675,265，流动性 1,708,528",
          "Alpha 列表口径 24h 成交额 11,043,825",
          "短周期波动 0.62%",
          "4h 振幅 4.51%",
          "审计风险 MID"
        ]
      },
      {
        "symbol": "LYN",
        "name": "Everlyn AI",
        "chain_id": "56",
        "contract_address": "0x302dfaf2cdbe51a18d97186a7384e87cf599877d",
        "alpha_id": "ALPHA_412",
        "alpha_trade_symbol": "ALPHA_412USDT",
        "alpha_trade_symbols": [
          "ALPHA_412USDT",
          "ALPHA_412USDC"
        ],
        "alpha_trade_tickers": [
          {
            "symbol": "ALPHA_412USDT",
            "quote_volume24h": 1053126.7942596,
            "base_volume24h": 15331217.83,
            "last_price": 0.06584163
          },
          {
            "symbol": "ALPHA_412USDC",
            "quote_volume24h": 161942.11255477,
            "base_volume24h": 2380089.98,
            "last_price": 0.06598366
          }
        ],
        "mul_point": 4,
        "price": 0.06581227856479939,
        "percent_change_24h": -3.35,
        "volume24h": 2376424.039138264,
        "token_list_volume24h": 2376424.039138264,
        "display_volume24h": 1215068.90681437,
        "display_volume_method": "alpha_trade_quote_volume",
        "alpha_trade_quote_volume24h": 1215068.90681437,
        "alpha_trade_base_volume24h": 17711307.81,
        "liquidity": 374790.4208355138,
        "holders": 23334,
        "count24h": 33391,
        "listing_time": "2026-02-25T10:00:00+00:00",
        "listing_time_ms": 1772013600000,
        "amplitude_24h_pct": 18.714428569013638,
        "estimated_participants": 148.1791349773622,
        "realized_volatility_pct": 0.627298663632429,
        "amplitude_4h_pct": 5.440514900882939,
        "trend_4h_pct": -3.1329620188803697,
        "stable_volume24h": 1215068.90681437,
        "audit_risk": "LOW",
        "audit_factor": 1.0,
        "stability_score": 24.15,
        "reason": [
          "Alpha Trade 24h 成交额 1,215,069，流动性 374,790",
          "Alpha 列表口径 24h 成交额 2,376,424",
          "短周期波动 0.63%",
          "4h 振幅 5.44%",
          "审计风险 LOW"
        ]
      }
    ],
    "summary": [
      "当前最适合稳定刷分的首选是 GUA，因为 Alpha Trade 成交额与流动性更高，短周期波动更可控。",
      "稳定刷分分数综合考虑 Alpha Trade 24h 成交额、流动性、持有人、短周期波动、4h 振幅与审计风险。"
    ]
  },
  "futures_alerts": {
    "matched_contract_count": 214,
    "alerts": [
      {
        "alpha_symbol": "G",
        "futures_symbol": "GUSDT",
        "price_change_percent_24h": 23.448,
        "quote_volume_24h": 25498598.812447,
        "funding_bps": -89.9526,
        "base_score": 116.01007589505541,
        "open_interest_change_5m_pct": 0.5560779496203594,
        "alert_score": 116.68,
        "should_notify": true,
        "reasons": [
          "24h 涨跌 23.45%",
          "24h 成交额 25,498,599",
          "资金费率 -89.95 bps",
          "5m 持仓变化 0.56%"
        ]
      },
      {
        "alpha_symbol": "KITE",
        "futures_symbol": "KITEUSDT",
        "price_change_percent_24h": -1.68,
        "quote_volume_24h": 33890314.57601,
        "funding_bps": -75.839,
        "base_score": 86.1652663201227,
        "open_interest_change_5m_pct": 0.0632604658293845,
        "alert_score": 86.24,
        "should_notify": true,
        "reasons": [
          "24h 涨跌 -1.68%",
          "24h 成交额 33,890,315",
          "资金费率 -75.84 bps",
          "5m 持仓变化 0.06%"
        ]
      },
      {
        "alpha_symbol": "LYN",
        "futures_symbol": "LYNUSDT",
        "price_change_percent_24h": -43.709,
        "quote_volume_24h": 207512380.72883,
        "funding_bps": -4.8414,
        "base_score": 57.62195682851299,
        "open_interest_change_5m_pct": 0.08965501286994915,
        "alert_score": 57.73,
        "should_notify": true,
        "reasons": [
          "24h 涨跌 -43.71%",
          "24h 成交额 207,512,381",
          "资金费率 -4.84 bps",
          "5m 持仓变化 0.09%"
        ]
      },
      {
        "alpha_symbol": "ATH",
        "futures_symbol": "ATHUSDT",
        "price_change_percent_24h": 9.888,
        "quote_volume_24h": 30410573.286865,
        "funding_bps": -25.609,
        "base_score": 47.42115413617324,
        "open_interest_change_5m_pct": -0.35947929058970374,
        "alert_score": 47.85,
        "should_notify": true,
        "reasons": [
          "24h 涨跌 9.89%",
          "24h 成交额 30,410,573",
          "资金费率 -25.61 bps",
          "5m 持仓变化 -0.36%"
        ]
      },
      {
        "alpha_symbol": "XAN",
        "futures_symbol": "XANUSDT",
        "price_change_percent_24h": 12.08,
        "quote_volume_24h": 538874196.354261,
        "funding_bps": -15.699200000000001,
        "base_score": 43.00255225399779,
        "open_interest_change_5m_pct": 1.8490547997878082,
        "alert_score": 45.22,
        "should_notify": true,
        "reasons": [
          "24h 涨跌 12.08%",
          "24h 成交额 538,874,196",
          "资金费率 -15.70 bps",
          "5m 持仓变化 1.85%"
        ]
      },
      {
        "alpha_symbol": "DEGEN",
        "futures_symbol": "DEGENUSDT",
        "price_change_percent_24h": 26.429,
        "quote_volume_24h": 20601627.8120007,
        "funding_bps": -0.8525999999999999,
        "base_score": 38.00112338131925,
        "open_interest_change_5m_pct": 0.28869640575743816,
        "alert_score": 38.35,
        "should_notify": true,
        "reasons": [
          "24h 涨跌 26.43%",
          "24h 成交额 20,601,628",
          "资金费率 -0.85 bps",
          "5m 持仓变化 0.29%"
        ]
      },
      {
        "alpha_symbol": "PTB",
        "futures_symbol": "PTBUSDT",
        "price_change_percent_24h": 12.01,
        "quote_volume_24h": 12843759.532313,
        "funding_bps": 12.7273,
        "base_score": 36.70169276493303,
        "open_interest_change_5m_pct": -0.05708890997121463,
        "alert_score": 36.77,
        "should_notify": true,
        "reasons": [
          "24h 涨跌 12.01%",
          "24h 成交额 12,843,760",
          "资金费率 12.73 bps",
          "5m 持仓变化 -0.06%"
        ]
      },
      {
        "alpha_symbol": "ROBO",
        "futures_symbol": "ROBOUSDT",
        "price_change_percent_24h": -7.953,
        "quote_volume_24h": 47367153.93955,
        "funding_bps": -14.1438,
        "base_score": 35.977870039940484,
        "open_interest_change_5m_pct": 0.3526400536827179,
        "alert_score": 36.4,
        "should_notify": true,
        "reasons": [
          "24h 涨跌 -7.95%",
          "24h 成交额 47,367,154",
          "资金费率 -14.14 bps",
          "5m 持仓变化 0.35%"
        ]
      }
    ]
  },
  "daily_brief": {
    "recent_alpha_listings": [
      {
        "symbol": "PLAY",
        "name": "PlaysOut",
        "mul_point": 1,
        "listing_time": "2026-03-23T08:38:32+00:00",
        "volume24h": 215339.39187563324,
        "percent_change_24h": 4.08
      }
    ],
    "official_updates": [
      {
        "catalog_id": 48,
        "catalog_name": "New Cryptocurrency Listing",
        "articles": [
          {
            "title": "Binance Futures Will Launch Multiple USDⓈ-Margined Equity Perpetual Contracts (2026-03-26)",
            "code": "1aa8f5f80e4a4afcab149e653fd3113d",
            "publish_time": "2026-03-24T16:40:42.248000+00:00",
            "support_url": "https://www.binance.com/en/support/announcement/detail/1aa8f5f80e4a4afcab149e653fd3113d",
            "api_url": "https://www.binance.com/bapi/composite/v1/public/cms/article/detail/query?articleCode=1aa8f5f80e4a4afcab149e653fd3113d",
            "summary": "This is a general Binance Exchange Notice. Products and services referred to here may not be available in your region. Fellow Binancians, To expand the list of trading choices off…"
          },
          {
            "title": "Binance Futures Will Launch PAYPUSDT USDⓈ-Margined Equity Perpetual Contract (2026-03-23)",
            "code": "eb32c90a26fd405d97ea0c4174d41d74",
            "publish_time": "2026-03-20T13:58:29.010000+00:00",
            "support_url": "https://www.binance.com/en/support/announcement/detail/eb32c90a26fd405d97ea0c4174d41d74",
            "api_url": "https://www.binance.com/bapi/composite/v1/public/cms/article/detail/query?articleCode=eb32c90a26fd405d97ea0c4174d41d74",
            "summary": "This is a general Binance Exchange Notice. Products and services referred to here may not be available in your region. Fellow Binancians, To expand the list of trading choices off…"
          },
          {
            "title": "Binance Futures Will List USDⓈ-M & COIN-M Quarterly 0925 Delivery Contracts",
            "code": "39998757afa54c85a80091896cecd62b",
            "publish_time": "2026-03-20T03:01:12.935000+00:00",
            "support_url": "https://www.binance.com/en/support/announcement/detail/39998757afa54c85a80091896cecd62b",
            "api_url": "https://www.binance.com/bapi/composite/v1/public/cms/article/detail/query?articleCode=39998757afa54c85a80091896cecd62b",
            "summary": "This is a general announcement. Products and services referred to here may not be available in your region. Fellow Binancians, Binance Futures will list the following USDⓈ-M and C…"
          }
        ]
      },
      {
        "catalog_id": 49,
        "catalog_name": "Latest Binance News",
        "articles": [
          {
            "title": "Binance Adds BRL (Brazilian Real) as New Collateral Asset on Binance VIP Loan - 2026-03-25",
            "code": "3c44d521fc3c4afb8163a04865123921",
            "publish_time": "2026-03-25T05:00:25.175000+00:00",
            "support_url": "https://www.binance.com/en/support/announcement/detail/3c44d521fc3c4afb8163a04865123921",
            "api_url": "https://www.binance.com/bapi/composite/v1/public/cms/article/detail/query?articleCode=3c44d521fc3c4afb8163a04865123921",
            "summary": "This is a general announcement. Products and services referred to here may not be available in your region. Fellow Binancians, Binance has added BRL (Brazilian Real) as a new coll…"
          },
          {
            "title": "Binance Soft Staking Now Supports Ethereum (ETH)",
            "code": "0f8071e9f6ec4924a4d996b0d801a954",
            "publish_time": "2026-03-25T04:00:09.182000+00:00",
            "support_url": "https://www.binance.com/en/support/announcement/detail/0f8071e9f6ec4924a4d996b0d801a954",
            "api_url": "https://www.binance.com/bapi/composite/v1/public/cms/article/detail/query?articleCode=0f8071e9f6ec4924a4d996b0d801a954",
            "summary": "This is a general announcement. Products and services referred to here may not be available in your region. Terms and conditions apply. Fellow Binancians, Binance is pleased to an…"
          },
          {
            "title": "Introducing Binance Ai Pro Beta",
            "code": "9035e912721848699805c8b09b7ca9bd",
            "publish_time": "2026-03-24T10:30:13.771000+00:00",
            "support_url": "https://www.binance.com/en/support/announcement/detail/9035e912721848699805c8b09b7ca9bd",
            "api_url": "https://www.binance.com/bapi/composite/v1/public/cms/article/detail/query?articleCode=9035e912721848699805c8b09b7ca9bd",
            "summary": "This is a general announcement. Products and services referred to here may not be available in your region. Fellow Binancians, &nbsp; We are excited to announce the launch of the…"
          }
        ]
      },
      {
        "catalog_id": 93,
        "catalog_name": "Latest Activities",
        "articles": [
          {
            "title": "South Asia Exclusive: Trade Options & Share the $20,000 Reward Pool",
            "code": "a9f507ab1c00425eb666c1ff8423077f",
            "publish_time": "2026-03-25T06:00:10.437000+00:00",
            "support_url": "https://www.binance.com/en/support/announcement/detail/a9f507ab1c00425eb666c1ff8423077f",
            "api_url": "https://www.binance.com/bapi/composite/v1/public/cms/article/detail/query?articleCode=a9f507ab1c00425eb666c1ff8423077f",
            "summary": "This is a general announcement and marketing communication. Products and services referred to here may not be available in your region. Fellow Binancians,&nbsp; Binance is bringin…"
          },
          {
            "title": "Binance Earn New Listing Special Offer: Subscribe to NIGHT Locked Products to Enjoy 200% APR for 7 Days",
            "code": "ac91a033a68a45a4b3e190b13e5f11a5",
            "publish_time": "2026-03-25T04:30:05.906000+00:00",
            "support_url": "https://www.binance.com/en/support/announcement/detail/ac91a033a68a45a4b3e190b13e5f11a5",
            "api_url": "https://www.binance.com/bapi/composite/v1/public/cms/article/detail/query?articleCode=ac91a033a68a45a4b3e190b13e5f11a5",
            "summary": "This is a general announcement. Products and services referred to here may not be available in your region. Sponsored rewards. Terms and conditions apply. Fellow Binancians, To ce…"
          },
          {
            "title": "GCC Exclusive: Enjoy Up to 30+% Bonus on All USDT Deposits",
            "code": "3f3fb7526a1a42268659879b2130966f",
            "publish_time": "2026-03-25T01:00:00+00:00",
            "support_url": "https://www.binance.com/en/support/announcement/detail/3f3fb7526a1a42268659879b2130966f",
            "api_url": "https://www.binance.com/bapi/composite/v1/public/cms/article/detail/query?articleCode=3f3fb7526a1a42268659879b2130966f",
            "summary": "This is a general announcement. Products and services referred to here may not be available in your region. Fellow Binancians, Binance is excited to launch an exclusive offer for…"
          }
        ]
      }
    ],
    "summary": [
      "过去 72 小时新增 Alpha 代币 1 个，其中四倍分 0 个。",
      "官方最新上新关注：Binance Futures Will Launch Multiple USDⓈ-Margined Equity Perpetual Contracts (2026-03-26)",
      "Latest Binance News：Binance Adds BRL (Brazilian Real) as New Collateral Asset on Binance VIP Loan - 2026-03-25",
      "Latest Activities：South Asia Exclusive: Trade Options & Share the $20,000 Reward Pool"
    ]
  },
  "warnings": [
    "futures_fallback: using previous valid futures snapshot"
  ]
}