{
  "skill": "binance-alpha-assistant",
  "generated_at": "2026-04-07T17:53:24.103420+00:00",
  "assumptions": {
    "participant_volume_standard": 8200,
    "alpha_kline_interval": "5m",
    "alpha_kline_limit": 48,
    "recent_listing_hours": 72
  },
  "quadruple_points": {
    "token_count": 11,
    "total_volume_24h": 1451100031.5020592,
    "total_alpha_trade_quote_volume_24h": 1451100031.5020592,
    "total_alpha_trade_base_volume_24h": 10356442884.349998,
    "total_token_list_volume24h": 72596946.2410483,
    "estimated_participants": 176963.41847586088,
    "volume_method": "alpha_trade_quote_volume_sum",
    "tokens": [
      {
        "symbol": "UP",
        "name": "Unitas",
        "chain_id": "56",
        "contract_address": "0x000008d2175f9aeaddb2430c26f8a6f73c5a0000",
        "alpha_id": "ALPHA_804",
        "alpha_trade_symbol": "ALPHA_804USDT",
        "alpha_trade_symbols": [
          "ALPHA_804USDT",
          "ALPHA_804USDC",
          "ALPHA_804U"
        ],
        "alpha_trade_tickers": [
          {
            "symbol": "ALPHA_804USDT",
            "quote_volume24h": 971268795.8053008,
            "base_volume24h": 4450407595.12,
            "last_price": 0.24975419
          },
          {
            "symbol": "ALPHA_804USDC",
            "quote_volume24h": 2280650.94059169,
            "base_volume24h": 9846361.08,
            "last_price": 0.24974058
          },
          {
            "symbol": "ALPHA_804U",
            "quote_volume24h": 18.50843232,
            "base_volume24h": 98.29,
            "last_price": 0.230396
          }
        ],
        "mul_point": 4,
        "price": 0.24979643369615867,
        "percent_change_24h": 36.58,
        "volume24h": 14802276.423396416,
        "token_list_volume24h": 14802276.423396416,
        "display_volume24h": 973549465.2543248,
        "display_volume_method": "alpha_trade_quote_volume",
        "alpha_trade_quote_volume24h": 973549465.2543248,
        "alpha_trade_base_volume24h": 4460254054.49,
        "liquidity": 1999417.317896816,
        "holders": 6572,
        "count24h": 57098,
        "listing_time": "2026-03-13T10:00:00+00:00",
        "listing_time_ms": 1773396000000,
        "amplitude_24h_pct": 68.77067633488323,
        "estimated_participants": 118725.54454321034
      },
      {
        "symbol": "BASED",
        "name": "Based",
        "chain_id": "56",
        "contract_address": "0x1d28d989f9e3ccb8b15d0cec601734514f958e4d",
        "alpha_id": "ALPHA_837",
        "alpha_trade_symbol": "ALPHA_837USDT",
        "alpha_trade_symbols": [
          "ALPHA_837USDT",
          "ALPHA_837USDC",
          "ALPHA_837U"
        ],
        "alpha_trade_tickers": [
          {
            "symbol": "ALPHA_837USDT",
            "quote_volume24h": 251834383.97171262,
            "base_volume24h": 4507039734.44,
            "last_price": 0.05987559
          },
          {
            "symbol": "ALPHA_837USDC",
            "quote_volume24h": 451133.94992243,
            "base_volume24h": 7958905.42,
            "last_price": 0.05962125
          },
          {
            "symbol": "ALPHA_837U",
            "quote_volume24h": 11.17205647,
            "base_volume24h": 184.45,
            "last_price": 0.05641358
          }
        ],
        "mul_point": 4,
        "price": 0.05990085578742193,
        "percent_change_24h": 6.42,
        "volume24h": 17108866.71076362,
        "token_list_volume24h": 17108866.71076362,
        "display_volume24h": 252285529.09369153,
        "display_volume_method": "alpha_trade_quote_volume",
        "alpha_trade_quote_volume24h": 252285529.09369153,
        "alpha_trade_base_volume24h": 4514998824.309999,
        "liquidity": 969221.0319534427,
        "holders": 3605,
        "count24h": 62434,
        "listing_time": "2026-03-30T08:00:00+00:00",
        "listing_time_ms": 1774857600000,
        "amplitude_24h_pct": 19.81587484814514,
        "estimated_participants": 30766.527938255065
      },
      {
        "symbol": "PRL",
        "name": "Perle",
        "chain_id": "56",
        "contract_address": "0xd20fb09a49a8e75fef536a2dbc68222900287bac",
        "alpha_id": "ALPHA_823",
        "alpha_trade_symbol": "ALPHA_823USDT",
        "alpha_trade_symbols": [
          "ALPHA_823USDT",
          "ALPHA_823USDC",
          "ALPHA_823U"
        ],
        "alpha_trade_tickers": [
          {
            "symbol": "ALPHA_823USDT",
            "quote_volume24h": 198050177.94209376,
            "base_volume24h": 1167481824.06,
            "last_price": 0.17137888
          },
          {
            "symbol": "ALPHA_823USDC",
            "quote_volume24h": 260947.10768213,
            "base_volume24h": 1519457.1,
            "last_price": 0.17154365
          },
          {
            "symbol": "ALPHA_823U",
            "quote_volume24h": 1001.6553,
            "base_volume24h": 5892.09,
            "last_price": 0.17
          }
        ],
        "mul_point": 4,
        "price": 0.17150792745169097,
        "percent_change_24h": -13.47,
        "volume24h": 6569680.900116469,
        "token_list_volume24h": 6569680.900116469,
        "display_volume24h": 198312126.7050759,
        "display_volume_method": "alpha_trade_quote_volume",
        "alpha_trade_quote_volume24h": 198312126.7050759,
        "alpha_trade_base_volume24h": 1169007173.2499998,
        "liquidity": 1385893.813711824,
        "holders": 1291,
        "count24h": 64564,
        "listing_time": "2026-03-25T10:00:00+00:00",
        "listing_time_ms": 1774432800000,
        "amplitude_24h_pct": 25.774608852178005,
        "estimated_participants": 24184.405695740963
      },
      {
        "symbol": "EDGE",
        "name": "edgeX",
        "chain_id": "56",
        "contract_address": "0x70f2eadf1ca1969ff42b0c78e9da519e8937cbaf",
        "alpha_id": "ALPHA_838",
        "alpha_trade_symbol": "ALPHA_838USDT",
        "alpha_trade_symbols": [
          "ALPHA_838USDT",
          "ALPHA_838USDC",
          "ALPHA_838U"
        ],
        "alpha_trade_tickers": [
          {
            "symbol": "ALPHA_838USDT",
            "quote_volume24h": 21988311.18132509,
            "base_volume24h": 22748067.65,
            "last_price": 1.05642806
          },
          {
            "symbol": "ALPHA_838USDC",
            "quote_volume24h": 265552.0331899,
            "base_volume24h": 267858.08,
            "last_price": 1.05899453
          },
          {
            "symbol": "ALPHA_838U",
            "quote_volume24h": 5.87673671,
            "base_volume24h": 6.75,
            "last_price": 0.87062766
          }
        ],
        "mul_point": 4,
        "price": 1.0569238166828034,
        "percent_change_24h": 16.59,
        "volume24h": 9596618.825373897,
        "token_list_volume24h": 9596618.825373897,
        "display_volume24h": 22253869.0912517,
        "display_volume_method": "alpha_trade_quote_volume",
        "alpha_trade_quote_volume24h": 22253869.0912517,
        "alpha_trade_base_volume24h": 23015932.479999997,
        "liquidity": 1386968.8054430056,
        "holders": 749,
        "count24h": 31814,
        "listing_time": "2026-03-31T12:30:00+00:00",
        "listing_time_ms": 1774960200000,
        "amplitude_24h_pct": 24.37291051047666,
        "estimated_participants": 2713.8864745428905
      },
      {
        "symbol": "SIGMA",
        "name": "SigmaDotMoney",
        "chain_id": "56",
        "contract_address": "0x85375d3e9c4a39350f1140280a8b0de6890a40e7",
        "alpha_id": "ALPHA_439",
        "alpha_trade_symbol": "ALPHA_439USDT",
        "alpha_trade_symbols": [
          "ALPHA_439USDT",
          "ALPHA_439USDC",
          "ALPHA_439U"
        ],
        "alpha_trade_tickers": [
          {
            "symbol": "ALPHA_439USDT",
            "quote_volume24h": 2474401.30740498,
            "base_volume24h": 119485176.05,
            "last_price": 0.0188
          },
          {
            "symbol": "ALPHA_439USDC",
            "quote_volume24h": 176658.00814866,
            "base_volume24h": 8369973.8,
            "last_price": 0.01884998
          },
          {
            "symbol": "ALPHA_439U",
            "quote_volume24h": 9074.62326192,
            "base_volume24h": 190388.1,
            "last_price": 0.02338109
          }
        ],
        "mul_point": 4,
        "price": 0.01888955621248761,
        "percent_change_24h": -16.68,
        "volume24h": 1364207.3774713676,
        "token_list_volume24h": 1364207.3774713676,
        "display_volume24h": 2660133.93881556,
        "display_volume_method": "alpha_trade_quote_volume",
        "alpha_trade_quote_volume24h": 2660133.93881556,
        "alpha_trade_base_volume24h": 128045537.94999999,
        "liquidity": 342145.3715792854,
        "holders": 34489,
        "count24h": 26366,
        "listing_time": "2026-03-10T00:00:00+00:00",
        "listing_time_ms": 1773100800000,
        "amplitude_24h_pct": 51.591907039638386,
        "estimated_participants": 324.4065779043366
      },
      {
        "symbol": "CYS",
        "name": "Cysic",
        "chain_id": "56",
        "contract_address": "0x0c69199c1562233640e0db5ce2c399a88eb507c7",
        "alpha_id": "ALPHA_495",
        "alpha_trade_symbol": "ALPHA_495USDT",
        "alpha_trade_symbols": [
          "ALPHA_495USDT",
          "ALPHA_495USDC",
          "ALPHA_495U"
        ],
        "alpha_trade_tickers": [
          {
            "symbol": "ALPHA_495USDT",
            "quote_volume24h": 901108.23620075,
            "base_volume24h": 3746780.14,
            "last_price": 0.23723626
          },
          {
            "symbol": "ALPHA_495USDC",
            "quote_volume24h": 68224.34210256,
            "base_volume24h": 287024.94,
            "last_price": 0.2375
          },
          {
            "symbol": "ALPHA_495U",
            "quote_volume24h": 0.22837299,
            "base_volume24h": 0.95,
            "last_price": 0.24039262
          }
        ],
        "mul_point": 4,
        "price": 0.2377942315750674,
        "percent_change_24h": 8.98,
        "volume24h": 7929881.620873381,
        "token_list_volume24h": 7929881.620873381,
        "display_volume24h": 969332.8066763,
        "display_volume_method": "alpha_trade_quote_volume",
        "alpha_trade_quote_volume24h": 969332.8066763,
        "alpha_trade_base_volume24h": 4033806.0300000003,
        "liquidity": 1198502.7661402093,
        "holders": 9282,
        "count24h": 37204,
        "listing_time": "2026-03-20T08:00:00+00:00",
        "listing_time_ms": 1773993600000,
        "amplitude_24h_pct": 33.51766519955309,
        "estimated_participants": 118.21131788735366
      },
      {
        "symbol": "LAB",
        "name": "LAB",
        "chain_id": "56",
        "contract_address": "0x7ec43cf65f1663f820427c62a5780b8f2e25593a",
        "alpha_id": "ALPHA_428",
        "alpha_trade_symbol": "ALPHA_428USDT",
        "alpha_trade_symbols": [
          "ALPHA_428USDT",
          "ALPHA_428USDC",
          "ALPHA_428U"
        ],
        "alpha_trade_tickers": [
          {
            "symbol": "ALPHA_428USDT",
            "quote_volume24h": 721642.5362518,
            "base_volume24h": 2286918.63,
            "last_price": 0.31980769
          },
          {
            "symbol": "ALPHA_428USDC",
            "quote_volume24h": 15447.50439478,
            "base_volume24h": 49732.11,
            "last_price": 0.31975544
          },
          {
            "symbol": "ALPHA_428U",
            "quote_volume24h": 0.0,
            "base_volume24h": 0.0,
            "last_price": null
          }
        ],
        "mul_point": 4,
        "price": 0.32038714176841643,
        "percent_change_24h": 11.3,
        "volume24h": 9207855.277856197,
        "token_list_volume24h": 9207855.277856197,
        "display_volume24h": 737090.04064658,
        "display_volume_method": "alpha_trade_quote_volume",
        "alpha_trade_quote_volume24h": 737090.04064658,
        "alpha_trade_base_volume24h": 2336650.7399999998,
        "liquidity": 2218264.435140198,
        "holders": 16968,
        "count24h": 64420,
        "listing_time": "2026-03-10T10:00:00+00:00",
        "listing_time_ms": 1773136800000,
        "amplitude_24h_pct": 18.109707224831755,
        "estimated_participants": 89.8890293471439
      },
      {
        "symbol": "TRADOOR",
        "name": "Tradoor",
        "chain_id": "56",
        "contract_address": "0x9123400446a56176eb1b6be9ee5cf703e409f492",
        "alpha_id": "ALPHA_356",
        "alpha_trade_symbol": "ALPHA_356USDT",
        "alpha_trade_symbols": [
          "ALPHA_356USDT",
          "ALPHA_356USDC",
          "ALPHA_356U"
        ],
        "alpha_trade_tickers": [
          {
            "symbol": "ALPHA_356USDT",
            "quote_volume24h": 121146.92671574,
            "base_volume24h": 37038.58,
            "last_price": 3.29763
          },
          {
            "symbol": "ALPHA_356USDC",
            "quote_volume24h": 7016.6669592,
            "base_volume24h": 2142.18,
            "last_price": 3.30511052
          },
          {
            "symbol": "ALPHA_356U",
            "quote_volume24h": 0.0,
            "base_volume24h": 0.0,
            "last_price": null
          }
        ],
        "mul_point": 4,
        "price": 3.299636054731744,
        "percent_change_24h": 3.53,
        "volume24h": 2096679.1277833986,
        "token_list_volume24h": 2096679.1277833986,
        "display_volume24h": 128163.59367494,
        "display_volume_method": "alpha_trade_quote_volume",
        "alpha_trade_quote_volume24h": 128163.59367494,
        "alpha_trade_base_volume24h": 39180.76,
        "liquidity": 1994626.618711067,
        "holders": 101516,
        "count24h": 7817,
        "listing_time": "2025-09-04T12:00:00+00:00",
        "listing_time_ms": 1756987200000,
        "amplitude_24h_pct": 8.922160674372776,
        "estimated_participants": 15.62970654572439
      },
      {
        "symbol": "AIA",
        "name": "DeAgentAI",
        "chain_id": "56",
        "contract_address": "0x53ec33cd4fa46b9eced9ca3f6db626c5ffcd55cc",
        "alpha_id": "ALPHA_496",
        "alpha_trade_symbol": "ALPHA_496USDT",
        "alpha_trade_symbols": [
          "ALPHA_496USDT",
          "ALPHA_496USDC",
          "ALPHA_496U"
        ],
        "alpha_trade_tickers": [
          {
            "symbol": "ALPHA_496USDT",
            "quote_volume24h": 81291.30666199,
            "base_volume24h": 688782.8,
            "last_price": 0.12382741
          },
          {
            "symbol": "ALPHA_496USDC",
            "quote_volume24h": 20431.57128444,
            "base_volume24h": 174208.68,
            "last_price": 0.12410425
          },
          {
            "symbol": "ALPHA_496U",
            "quote_volume24h": 1.9189436,
            "base_volume24h": 19.35,
            "last_price": 0.09858047
          }
        ],
        "mul_point": 4,
        "price": 0.12319394864690328,
        "percent_change_24h": 8.41,
        "volume24h": 3678590.8939292333,
        "token_list_volume24h": 3678590.8939292333,
        "display_volume24h": 101724.79689003,
        "display_volume_method": "alpha_trade_quote_volume",
        "alpha_trade_quote_volume24h": 101724.79689003,
        "alpha_trade_base_volume24h": 863010.83,
        "liquidity": 929058.4998922573,
        "holders": 2605,
        "count24h": 21674,
        "listing_time": "2026-03-10T00:00:00+00:00",
        "listing_time_ms": 1773100800000,
        "amplitude_24h_pct": 18.437776441111815,
        "estimated_participants": 12.405463035369513
      },
      {
        "symbol": "R2",
        "name": "R2 Protocol",
        "chain_id": "56",
        "contract_address": "0x223a20e1b83aa3832e78d4b7b132df022e739222",
        "alpha_id": "ALPHA_836",
        "alpha_trade_symbol": "ALPHA_836USDT",
        "alpha_trade_symbols": [
          "ALPHA_836USDT",
          "ALPHA_836USDC",
          "ALPHA_836U"
        ],
        "alpha_trade_tickers": [
          {
            "symbol": "ALPHA_836USDT",
            "quote_volume24h": 43995.06371941,
            "base_volume24h": 10148738.96,
            "last_price": 0.00404106
          },
          {
            "symbol": "ALPHA_836USDC",
            "quote_volume24h": 12313.22449913,
            "base_volume24h": 2813900.17,
            "last_price": 0.00396174
          },
          {
            "symbol": "ALPHA_836U",
            "quote_volume24h": 3.17366047,
            "base_volume24h": 723.17,
            "last_price": 0.00438854
          }
        ],
        "mul_point": 4,
        "price": 0.00398649768600428,
        "percent_change_24h": -8.22,
        "volume24h": 107127.21316805872,
        "token_list_volume24h": 107127.21316805872,
        "display_volume24h": 56311.46187900999,
        "display_volume_method": "alpha_trade_quote_volume",
        "alpha_trade_quote_volume24h": 56311.46187900999,
        "alpha_trade_base_volume24h": 12963362.3,
        "liquidity": 243894.83105797326,
        "holders": 5040,
        "count24h": 1476,
        "listing_time": "2026-03-30T10:00:00+00:00",
        "listing_time_ms": 1774864800000,
        "amplitude_24h_pct": 26.65592403644433,
        "estimated_participants": 6.867251448659755
      },
      {
        "symbol": "SN3",
        "name": "Nebula3",
        "chain_id": "56",
        "contract_address": "0xf758cfb1467a227516d73d87da7d36e7cb6f71f1",
        "alpha_id": "ALPHA_798",
        "alpha_trade_symbol": "ALPHA_798USDT",
        "alpha_trade_symbols": [
          "ALPHA_798USDT",
          "ALPHA_798USDC",
          "ALPHA_798U"
        ],
        "alpha_trade_tickers": [
          {
            "symbol": "ALPHA_798USDT",
            "quote_volume24h": 30014.91899761,
            "base_volume24h": 26560676.21,
            "last_price": 0.0010558
          },
          {
            "symbol": "ALPHA_798USDC",
            "quote_volume24h": 16269.34498129,
            "base_volume24h": 14324335.14,
            "last_price": 0.00103635
          },
          {
            "symbol": "ALPHA_798U",
            "quote_volume24h": 0.45515411,
            "base_volume24h": 339.86,
            "last_price": 0.00133924
          }
        ],
        "mul_point": 4,
        "price": 0.0010437539735782119,
        "percent_change_24h": 1.32,
        "volume24h": 135161.87031626323,
        "token_list_volume24h": 135161.87031626323,
        "display_volume24h": 46284.719133009996,
        "display_volume_method": "alpha_trade_quote_volume",
        "alpha_trade_quote_volume24h": 46284.719133009996,
        "alpha_trade_base_volume24h": 40885351.21,
        "liquidity": 109465.53657466936,
        "holders": 2290,
        "count24h": 2015,
        "listing_time": "2026-03-11T08:00:00+00:00",
        "listing_time_ms": 1773216000000,
        "amplitude_24h_pct": 36.788334725441246,
        "estimated_participants": 5.644477943049999
      }
    ]
  },
  "stable_candidates": {
    "analyzed_count": 7,
    "recommendations": [
      {
        "symbol": "LAB",
        "name": "LAB",
        "chain_id": "56",
        "contract_address": "0x7ec43cf65f1663f820427c62a5780b8f2e25593a",
        "alpha_id": "ALPHA_428",
        "alpha_trade_symbol": "ALPHA_428USDT",
        "alpha_trade_symbols": [
          "ALPHA_428USDT",
          "ALPHA_428USDC",
          "ALPHA_428U"
        ],
        "alpha_trade_tickers": [
          {
            "symbol": "ALPHA_428USDT",
            "quote_volume24h": 721642.5362518,
            "base_volume24h": 2286918.63,
            "last_price": 0.31980769
          },
          {
            "symbol": "ALPHA_428USDC",
            "quote_volume24h": 15447.50439478,
            "base_volume24h": 49732.11,
            "last_price": 0.31975544
          },
          {
            "symbol": "ALPHA_428U",
            "quote_volume24h": 0.0,
            "base_volume24h": 0.0,
            "last_price": null
          }
        ],
        "mul_point": 4,
        "price": 0.32038714176841643,
        "percent_change_24h": 11.3,
        "volume24h": 9207855.277856197,
        "token_list_volume24h": 9207855.277856197,
        "display_volume24h": 737090.04064658,
        "display_volume_method": "alpha_trade_quote_volume",
        "alpha_trade_quote_volume24h": 737090.04064658,
        "alpha_trade_base_volume24h": 2336650.7399999998,
        "liquidity": 2218264.435140198,
        "holders": 16968,
        "count24h": 64420,
        "listing_time": "2026-03-10T10:00:00+00:00",
        "listing_time_ms": 1773136800000,
        "amplitude_24h_pct": 18.109707224831755,
        "estimated_participants": 89.8890293471439,
        "realized_volatility_pct": 0.46790431419509626,
        "amplitude_4h_pct": 4.4857196029776665,
        "trend_4h_pct": -0.8040663771712309,
        "stable_volume24h": 737090.04064658,
        "audit_risk": "LOW",
        "audit_factor": 1.0,
        "stability_score": 67.21,
        "reason": [
          "Alpha Trade 24h 成交额 737,090，流动性 2,218,264",
          "Alpha 列表口径 24h 成交额 9,207,855",
          "短周期波动 0.47%",
          "4h 振幅 4.49%",
          "审计风险 LOW"
        ]
      },
      {
        "symbol": "PRL",
        "name": "Perle",
        "chain_id": "56",
        "contract_address": "0xd20fb09a49a8e75fef536a2dbc68222900287bac",
        "alpha_id": "ALPHA_823",
        "alpha_trade_symbol": "ALPHA_823USDT",
        "alpha_trade_symbols": [
          "ALPHA_823USDT",
          "ALPHA_823USDC",
          "ALPHA_823U"
        ],
        "alpha_trade_tickers": [
          {
            "symbol": "ALPHA_823USDT",
            "quote_volume24h": 198050177.94209376,
            "base_volume24h": 1167481824.06,
            "last_price": 0.17137888
          },
          {
            "symbol": "ALPHA_823USDC",
            "quote_volume24h": 260947.10768213,
            "base_volume24h": 1519457.1,
            "last_price": 0.17154365
          },
          {
            "symbol": "ALPHA_823U",
            "quote_volume24h": 1001.6553,
            "base_volume24h": 5892.09,
            "last_price": 0.17
          }
        ],
        "mul_point": 4,
        "price": 0.17150792745169097,
        "percent_change_24h": -13.47,
        "volume24h": 6569680.900116469,
        "token_list_volume24h": 6569680.900116469,
        "display_volume24h": 198312126.7050759,
        "display_volume_method": "alpha_trade_quote_volume",
        "alpha_trade_quote_volume24h": 198312126.7050759,
        "alpha_trade_base_volume24h": 1169007173.2499998,
        "liquidity": 1385893.813711824,
        "holders": 1291,
        "count24h": 64564,
        "listing_time": "2026-03-25T10:00:00+00:00",
        "listing_time_ms": 1774432800000,
        "amplitude_24h_pct": 25.774608852178005,
        "estimated_participants": 24184.405695740963,
        "realized_volatility_pct": 0.6640662117679444,
        "amplitude_4h_pct": 6.8575650793494995,
        "trend_4h_pct": 0.15730522693333526,
        "stable_volume24h": 198312126.7050759,
        "audit_risk": "LOW",
        "audit_factor": 1.0,
        "stability_score": 51.49,
        "reason": [
          "Alpha Trade 24h 成交额 198,312,127，流动性 1,385,894",
          "Alpha 列表口径 24h 成交额 6,569,681",
          "短周期波动 0.66%",
          "4h 振幅 6.86%",
          "审计风险 LOW"
        ]
      },
      {
        "symbol": "UP",
        "name": "Unitas",
        "chain_id": "56",
        "contract_address": "0x000008d2175f9aeaddb2430c26f8a6f73c5a0000",
        "alpha_id": "ALPHA_804",
        "alpha_trade_symbol": "ALPHA_804USDT",
        "alpha_trade_symbols": [
          "ALPHA_804USDT",
          "ALPHA_804USDC",
          "ALPHA_804U"
        ],
        "alpha_trade_tickers": [
          {
            "symbol": "ALPHA_804USDT",
            "quote_volume24h": 971268795.8053008,
            "base_volume24h": 4450407595.12,
            "last_price": 0.24975419
          },
          {
            "symbol": "ALPHA_804USDC",
            "quote_volume24h": 2280650.94059169,
            "base_volume24h": 9846361.08,
            "last_price": 0.24974058
          },
          {
            "symbol": "ALPHA_804U",
            "quote_volume24h": 18.50843232,
            "base_volume24h": 98.29,
            "last_price": 0.230396
          }
        ],
        "mul_point": 4,
        "price": 0.24979643369615867,
        "percent_change_24h": 36.58,
        "volume24h": 14802276.423396416,
        "token_list_volume24h": 14802276.423396416,
        "display_volume24h": 973549465.2543248,
        "display_volume_method": "alpha_trade_quote_volume",
        "alpha_trade_quote_volume24h": 973549465.2543248,
        "alpha_trade_base_volume24h": 4460254054.49,
        "liquidity": 1999417.317896816,
        "holders": 6572,
        "count24h": 57098,
        "listing_time": "2026-03-13T10:00:00+00:00",
        "listing_time_ms": 1773396000000,
        "amplitude_24h_pct": 68.77067633488323,
        "estimated_participants": 118725.54454321034,
        "realized_volatility_pct": 1.7011563767320752,
        "amplitude_4h_pct": 17.890896455872127,
        "trend_4h_pct": -13.233676164002784,
        "stable_volume24h": 973549465.2543248,
        "audit_risk": "MID",
        "audit_factor": 0.6,
        "stability_score": 51.26,
        "reason": [
          "Alpha Trade 24h 成交额 973,549,465，流动性 1,999,417",
          "Alpha 列表口径 24h 成交额 14,802,276",
          "短周期波动 1.70%",
          "4h 振幅 17.89%",
          "审计风险 MID"
        ]
      },
      {
        "symbol": "SIGMA",
        "name": "SigmaDotMoney",
        "chain_id": "56",
        "contract_address": "0x85375d3e9c4a39350f1140280a8b0de6890a40e7",
        "alpha_id": "ALPHA_439",
        "alpha_trade_symbol": "ALPHA_439USDT",
        "alpha_trade_symbols": [
          "ALPHA_439USDT",
          "ALPHA_439USDC",
          "ALPHA_439U"
        ],
        "alpha_trade_tickers": [
          {
            "symbol": "ALPHA_439USDT",
            "quote_volume24h": 2474401.30740498,
            "base_volume24h": 119485176.05,
            "last_price": 0.0188
          },
          {
            "symbol": "ALPHA_439USDC",
            "quote_volume24h": 176658.00814866,
            "base_volume24h": 8369973.8,
            "last_price": 0.01884998
          },
          {
            "symbol": "ALPHA_439U",
            "quote_volume24h": 9074.62326192,
            "base_volume24h": 190388.1,
            "last_price": 0.02338109
          }
        ],
        "mul_point": 4,
        "price": 0.01888955621248761,
        "percent_change_24h": -16.68,
        "volume24h": 1364207.3774713676,
        "token_list_volume24h": 1364207.3774713676,
        "display_volume24h": 2660133.93881556,
        "display_volume_method": "alpha_trade_quote_volume",
        "alpha_trade_quote_volume24h": 2660133.93881556,
        "alpha_trade_base_volume24h": 128045537.94999999,
        "liquidity": 342145.3715792854,
        "holders": 34489,
        "count24h": 26366,
        "listing_time": "2026-03-10T00:00:00+00:00",
        "listing_time_ms": 1773100800000,
        "amplitude_24h_pct": 51.591907039638386,
        "estimated_participants": 324.4065779043366,
        "realized_volatility_pct": 1.1464275270714823,
        "amplitude_4h_pct": 10.762586387989108,
        "trend_4h_pct": 3.709718703937437,
        "stable_volume24h": 2660133.93881556,
        "audit_risk": "LOW",
        "audit_factor": 1.0,
        "stability_score": 39.36,
        "reason": [
          "Alpha Trade 24h 成交额 2,660,134，流动性 342,145",
          "Alpha 列表口径 24h 成交额 1,364,207",
          "短周期波动 1.15%",
          "4h 振幅 10.76%",
          "审计风险 LOW"
        ]
      },
      {
        "symbol": "EDGE",
        "name": "edgeX",
        "chain_id": "56",
        "contract_address": "0x70f2eadf1ca1969ff42b0c78e9da519e8937cbaf",
        "alpha_id": "ALPHA_838",
        "alpha_trade_symbol": "ALPHA_838USDT",
        "alpha_trade_symbols": [
          "ALPHA_838USDT",
          "ALPHA_838USDC",
          "ALPHA_838U"
        ],
        "alpha_trade_tickers": [
          {
            "symbol": "ALPHA_838USDT",
            "quote_volume24h": 21988311.18132509,
            "base_volume24h": 22748067.65,
            "last_price": 1.05642806
          },
          {
            "symbol": "ALPHA_838USDC",
            "quote_volume24h": 265552.0331899,
            "base_volume24h": 267858.08,
            "last_price": 1.05899453
          },
          {
            "symbol": "ALPHA_838U",
            "quote_volume24h": 5.87673671,
            "base_volume24h": 6.75,
            "last_price": 0.87062766
          }
        ],
        "mul_point": 4,
        "price": 1.0569238166828034,
        "percent_change_24h": 16.59,
        "volume24h": 9596618.825373897,
        "token_list_volume24h": 9596618.825373897,
        "display_volume24h": 22253869.0912517,
        "display_volume_method": "alpha_trade_quote_volume",
        "alpha_trade_quote_volume24h": 22253869.0912517,
        "alpha_trade_base_volume24h": 23015932.479999997,
        "liquidity": 1386968.8054430056,
        "holders": 749,
        "count24h": 31814,
        "listing_time": "2026-03-31T12:30:00+00:00",
        "listing_time_ms": 1774960200000,
        "amplitude_24h_pct": 24.37291051047666,
        "estimated_participants": 2713.8864745428905,
        "realized_volatility_pct": 0.9485878574580205,
        "amplitude_4h_pct": 11.33045077789362,
        "trend_4h_pct": 3.4052102243795623,
        "stable_volume24h": 22253869.0912517,
        "audit_risk": "LOW",
        "audit_factor": 1.0,
        "stability_score": 38.79,
        "reason": [
          "Alpha Trade 24h 成交额 22,253,869，流动性 1,386,969",
          "Alpha 列表口径 24h 成交额 9,596,619",
          "短周期波动 0.95%",
          "4h 振幅 11.33%",
          "审计风险 LOW"
        ]
      }
    ],
    "summary": [
      "当前最适合稳定刷分的首选是 LAB，因为 Alpha Trade 成交额与流动性更高，短周期波动更可控。",
      "稳定刷分分数综合考虑 Alpha Trade 24h 成交额、流动性、持有人、短周期波动、4h 振幅与审计风险。"
    ]
  },
  "futures_alerts": {
    "matched_contract_count": 214,
    "alerts": [
      {
        "alpha_symbol": "G",
        "futures_symbol": "GUSDT",
        "price_change_percent_24h": 23.448,
        "quote_volume_24h": 25498598.812447,
        "funding_bps": -89.9526,
        "base_score": 116.01007589505541,
        "open_interest_change_5m_pct": 0.5560779496203594,
        "alert_score": 116.68,
        "should_notify": true,
        "reasons": [
          "24h 涨跌 23.45%",
          "24h 成交额 25,498,599",
          "资金费率 -89.95 bps",
          "5m 持仓变化 0.56%"
        ]
      },
      {
        "alpha_symbol": "KITE",
        "futures_symbol": "KITEUSDT",
        "price_change_percent_24h": -1.68,
        "quote_volume_24h": 33890314.57601,
        "funding_bps": -75.839,
        "base_score": 86.1652663201227,
        "open_interest_change_5m_pct": 0.0632604658293845,
        "alert_score": 86.24,
        "should_notify": true,
        "reasons": [
          "24h 涨跌 -1.68%",
          "24h 成交额 33,890,315",
          "资金费率 -75.84 bps",
          "5m 持仓变化 0.06%"
        ]
      },
      {
        "alpha_symbol": "LYN",
        "futures_symbol": "LYNUSDT",
        "price_change_percent_24h": -43.709,
        "quote_volume_24h": 207512380.72883,
        "funding_bps": -4.8414,
        "base_score": 57.62195682851299,
        "open_interest_change_5m_pct": 0.08965501286994915,
        "alert_score": 57.73,
        "should_notify": true,
        "reasons": [
          "24h 涨跌 -43.71%",
          "24h 成交额 207,512,381",
          "资金费率 -4.84 bps",
          "5m 持仓变化 0.09%"
        ]
      },
      {
        "alpha_symbol": "ATH",
        "futures_symbol": "ATHUSDT",
        "price_change_percent_24h": 9.888,
        "quote_volume_24h": 30410573.286865,
        "funding_bps": -25.609,
        "base_score": 47.42115413617324,
        "open_interest_change_5m_pct": -0.35947929058970374,
        "alert_score": 47.85,
        "should_notify": true,
        "reasons": [
          "24h 涨跌 9.89%",
          "24h 成交额 30,410,573",
          "资金费率 -25.61 bps",
          "5m 持仓变化 -0.36%"
        ]
      },
      {
        "alpha_symbol": "XAN",
        "futures_symbol": "XANUSDT",
        "price_change_percent_24h": 12.08,
        "quote_volume_24h": 538874196.354261,
        "funding_bps": -15.699200000000001,
        "base_score": 43.00255225399779,
        "open_interest_change_5m_pct": 1.8490547997878082,
        "alert_score": 45.22,
        "should_notify": true,
        "reasons": [
          "24h 涨跌 12.08%",
          "24h 成交额 538,874,196",
          "资金费率 -15.70 bps",
          "5m 持仓变化 1.85%"
        ]
      },
      {
        "alpha_symbol": "DEGEN",
        "futures_symbol": "DEGENUSDT",
        "price_change_percent_24h": 26.429,
        "quote_volume_24h": 20601627.8120007,
        "funding_bps": -0.8525999999999999,
        "base_score": 38.00112338131925,
        "open_interest_change_5m_pct": 0.28869640575743816,
        "alert_score": 38.35,
        "should_notify": true,
        "reasons": [
          "24h 涨跌 26.43%",
          "24h 成交额 20,601,628",
          "资金费率 -0.85 bps",
          "5m 持仓变化 0.29%"
        ]
      },
      {
        "alpha_symbol": "PTB",
        "futures_symbol": "PTBUSDT",
        "price_change_percent_24h": 12.01,
        "quote_volume_24h": 12843759.532313,
        "funding_bps": 12.7273,
        "base_score": 36.70169276493303,
        "open_interest_change_5m_pct": -0.05708890997121463,
        "alert_score": 36.77,
        "should_notify": true,
        "reasons": [
          "24h 涨跌 12.01%",
          "24h 成交额 12,843,760",
          "资金费率 12.73 bps",
          "5m 持仓变化 -0.06%"
        ]
      },
      {
        "alpha_symbol": "ROBO",
        "futures_symbol": "ROBOUSDT",
        "price_change_percent_24h": -7.953,
        "quote_volume_24h": 47367153.93955,
        "funding_bps": -14.1438,
        "base_score": 35.977870039940484,
        "open_interest_change_5m_pct": 0.3526400536827179,
        "alert_score": 36.4,
        "should_notify": true,
        "reasons": [
          "24h 涨跌 -7.95%",
          "24h 成交额 47,367,154",
          "资金费率 -14.14 bps",
          "5m 持仓变化 0.35%"
        ]
      }
    ]
  },
  "daily_brief": {
    "recent_alpha_listings": [],
    "official_updates": [
      {
        "catalog_id": 48,
        "catalog_name": "New Cryptocurrency Listing",
        "articles": [
          {
            "title": "Binance Futures Will Launch MUUSDT and SNDKUSDT USDⓈ-Margined Equity Perpetual Contracts (2026-04-07)",
            "code": "80549fadb3e447d1a859b8cedd0ccd69",
            "publish_time": "2026-04-03T13:30:07.828000+00:00",
            "support_url": "https://www.binance.com/en/support/announcement/detail/80549fadb3e447d1a859b8cedd0ccd69",
            "api_url": "https://www.binance.com/bapi/composite/v1/public/cms/article/detail/query?articleCode=80549fadb3e447d1a859b8cedd0ccd69",
            "summary": "This is a general Binance Exchange Notice. Products and services referred to here may not be available in your region. Fellow Binancians, To expand the list of trading choices off…"
          },
          {
            "title": "Binance Futures Will Launch QQQUSDT, SPYUSDT, AAPLUSDT and TSMUSDT USDⓈ-Margined Perpetual Contracts (2026-04-06)",
            "code": "4cde981dc32d4268b7645e9d16e8d63a",
            "publish_time": "2026-04-02T09:15:03.208000+00:00",
            "support_url": "https://www.binance.com/en/support/announcement/detail/4cde981dc32d4268b7645e9d16e8d63a",
            "api_url": "https://www.binance.com/bapi/composite/v1/public/cms/article/detail/query?articleCode=4cde981dc32d4268b7645e9d16e8d63a",
            "summary": "This is a general Binance Exchange Notice. Products and services referred to here may not be available in your region. Fellow Binancians, To expand the list of trading choices off…"
          },
          {
            "title": "Binance Futures Will Launch USDⓈ-Margined PRLUSDT Perpetual Contract (2026-04-01)",
            "code": "0116dd83010043bd95c37626e2277bbe",
            "publish_time": "2026-04-01T09:51:00.284000+00:00",
            "support_url": "https://www.binance.com/en/support/announcement/detail/0116dd83010043bd95c37626e2277bbe",
            "api_url": "https://www.binance.com/bapi/composite/v1/public/cms/article/detail/query?articleCode=0116dd83010043bd95c37626e2277bbe",
            "summary": "This is a general Binance Exchange Notice. Products and services referred to here may not be available in your region. Fellow Binancians, To expand the list of trading choices off…"
          }
        ]
      },
      {
        "catalog_id": 49,
        "catalog_name": "Latest Binance News",
        "articles": [
          {
            "title": "Update on the Collateral Ratio Under the Leverage & Margin Tiers of USDⓈ-M Perpetual Contracts (2026-04-10)",
            "code": "5a1c6a6e8dff4456b6e4710482eaaeec",
            "publish_time": "2026-04-07T07:30:07.882000+00:00",
            "support_url": "https://www.binance.com/en/support/announcement/detail/5a1c6a6e8dff4456b6e4710482eaaeec",
            "api_url": "https://www.binance.com/bapi/composite/v1/public/cms/article/detail/query?articleCode=5a1c6a6e8dff4456b6e4710482eaaeec",
            "summary": "This is a general announcement. Products and services referred to here may not be available in your region. Fellow Binancians, Binance Futures will update at 2026-04-10 06:30 (UTC…"
          },
          {
            "title": "Binance Introduces Spot Price Range Execution Rule (PRER)",
            "code": "185ae91a927c45fdaefcfaca76defcf8",
            "publish_time": "2026-04-07T07:00:12.043000+00:00",
            "support_url": "https://www.binance.com/en/support/announcement/detail/185ae91a927c45fdaefcfaca76defcf8",
            "api_url": "https://www.binance.com/bapi/composite/v1/public/cms/article/detail/query?articleCode=185ae91a927c45fdaefcfaca76defcf8",
            "summary": "*Starting on 2026-04-14, PRER will be gradually introduced to ensure a smooth and seamless transition. For more information, please refer to this page .&nbsp; This is a general an…"
          },
          {
            "title": "Updates on Tick Size for Spot Trading Pairs (2026-04-14)",
            "code": "1f1ee792db2d445eb967aa09f6c05138",
            "publish_time": "2026-04-07T03:00:08.211000+00:00",
            "support_url": "https://www.binance.com/en/support/announcement/detail/1f1ee792db2d445eb967aa09f6c05138",
            "api_url": "https://www.binance.com/bapi/composite/v1/public/cms/article/detail/query?articleCode=1f1ee792db2d445eb967aa09f6c05138",
            "summary": "This is a general announcement. Products and services referred to here may not be available in your region. Fellow Binancians, In order to increase market liquidity and improve tr…"
          }
        ]
      },
      {
        "catalog_id": 93,
        "catalog_name": "Latest Activities",
        "articles": [
          {
            "title": "Binance Academy Bitcoin Page: Complete Quiz to Earn BTC Rewards This April 2026!",
            "code": "586c9ff1b7d1489f8c31a0523517690f",
            "publish_time": "2026-04-07T00:00:00+00:00",
            "support_url": "https://www.binance.com/en/support/announcement/detail/586c9ff1b7d1489f8c31a0523517690f",
            "api_url": "https://www.binance.com/bapi/composite/v1/public/cms/article/detail/query?articleCode=586c9ff1b7d1489f8c31a0523517690f",
            "summary": "This is a general announcement. Products and services referred to here may not be available in your region. Fellow Binancians, Binance Academy is pleased to announce that the Bitc…"
          },
          {
            "title": "Binance Upsized KGST Booster Program: Enjoy Up to 12% APR with KGST Flexible Products (2026-04-07)",
            "code": "fc74f82d4d114221a12d9b114456536b",
            "publish_time": "2026-04-06T08:00:12.937000+00:00",
            "support_url": "https://www.binance.com/en/support/announcement/detail/fc74f82d4d114221a12d9b114456536b",
            "api_url": "https://www.binance.com/bapi/composite/v1/public/cms/article/detail/query?articleCode=fc74f82d4d114221a12d9b114456536b",
            "summary": "This is a general announcement and marketing communication. Products and services referred to here may not be available in your region. Terms and conditions apply. Fellow Binancia…"
          },
          {
            "title": "Team Up with Binance: Invite Friends and Share $400,000 Worth of WAL in Rewards",
            "code": "32efafb3054746d28c82d8023ae52465",
            "publish_time": "2026-04-06T04:00:13.424000+00:00",
            "support_url": "https://www.binance.com/en/support/announcement/detail/32efafb3054746d28c82d8023ae52465",
            "api_url": "https://www.binance.com/bapi/composite/v1/public/cms/article/detail/query?articleCode=32efafb3054746d28c82d8023ae52465",
            "summary": "This is a general announcement. Products and services referred to here may not be available in your region. Terms and conditions apply.&nbsp; Fellow Binancians, With the world gea…"
          }
        ]
      }
    ],
    "summary": [
      "官方最新上新关注：Binance Futures Will Launch MUUSDT and SNDKUSDT USDⓈ-Margined Equity Perpetual Contracts (2026-04-07)",
      "Latest Binance News：Update on the Collateral Ratio Under the Leverage & Margin Tiers of USDⓈ-M Perpetual Contracts (2026-04-10)",
      "Latest Activities：Binance Academy Bitcoin Page: Complete Quiz to Earn BTC Rewards This April 2026!"
    ]
  },
  "warnings": [
    "futures_fallback: using previous valid futures snapshot"
  ]
}